{
  "a_comp_cor_00": {
    "CumulativeVarianceExplained": 0.0716687286,
    "Mask": "CSF",
    "Method": "aCompCor",
    "Retained": true,
    "SingularValue": 87.271869033,
    "VarianceExplained": 0.0716687286
  },
  "a_comp_cor_01": {
    "CumulativeVarianceExplained": 0.1154468239,
    "Mask": "CSF",
    "Method": "aCompCor",
    "Retained": true,
    "SingularValue": 68.208399386,
    "VarianceExplained": 0.0437780953
  },
  "a_comp_cor_02": {
    "CumulativeVarianceExplained": 0.1500658161,
    "Mask": "CSF",
    "Method": "aCompCor",
    "Retained": true,
    "SingularValue": 60.655004198,
    "VarianceExplained": 0.0346189922
  },
  "a_comp_cor_03": {
    "CumulativeVarianceExplained": 0.1723919328,
    "Mask": "CSF",
    "Method": "aCompCor",
    "Retained": true,
    "SingularValue": 48.7097636738,
    "VarianceExplained": 0.0223261167
  },
  "a_comp_cor_04": {
    "CumulativeVarianceExplained": 0.1933274161,
    "Mask": "CSF",
    "Method": "aCompCor",
    "Retained": true,
    "SingularValue": 47.1683758461,
    "VarianceExplained": 0.0209354833
  },
  "a_comp_cor_05": {
    "CumulativeVarianceExplained": 0.2116220189,
    "Mask": "CSF",
    "Method": "aCompCor",
    "Retained": true,
    "SingularValue": 44.0931290995,
    "VarianceExplained": 0.0182946028
  },
  "a_comp_cor_06": {
    "CumulativeVarianceExplained": 0.2288962158,
    "Mask": "CSF",
    "Method": "aCompCor",
    "Retained": true,
    "SingularValue": 42.8458101193,
    "VarianceExplained": 0.0172741968
  },
  "a_comp_cor_07": {
    "CumulativeVarianceExplained": 0.2456957025,
    "Mask": "CSF",
    "Method": "aCompCor",
    "Retained": true,
    "SingularValue": 42.2529886782,
    "VarianceExplained": 0.0167994867
  },
  "a_comp_cor_08": {
    "CumulativeVarianceExplained": 0.261816638,
    "Mask": "CSF",
    "Method": "aCompCor",
    "Retained": true,
    "SingularValue": 41.3908692652,
    "VarianceExplained": 0.0161209355
  },
  "a_comp_cor_09": {
    "CumulativeVarianceExplained": 0.2764169782,
    "Mask": "CSF",
    "Method": "aCompCor",
    "Retained": true,
    "SingularValue": 39.3904474756,
    "VarianceExplained": 0.0146003402
  },
  "a_comp_cor_10": {
    "CumulativeVarianceExplained": 0.2905177264,
    "Mask": "CSF",
    "Method": "aCompCor",
    "Retained": true,
    "SingularValue": 38.7106537128,
    "VarianceExplained": 0.0141007482
  },
  "a_comp_cor_100": {
    "CumulativeVarianceExplained": 0.158225236,
    "Mask": "combined",
    "Method": "aCompCor",
    "Retained": true,
    "SingularValue": 150.5128112515,
    "VarianceExplained": 0.0091810824
  },
  "a_comp_cor_101": {
    "CumulativeVarianceExplained": 0.1670172885,
    "Mask": "combined",
    "Method": "aCompCor",
    "Retained": true,
    "SingularValue": 147.2894573527,
    "VarianceExplained": 0.0087920525
  },
  "a_comp_cor_102": {
    "CumulativeVarianceExplained": 0.1757148354,
    "Mask": "combined",
    "Method": "aCompCor",
    "Retained": true,
    "SingularValue": 146.4957136474,
    "VarianceExplained": 0.008697547
  },
  "a_comp_cor_103": {
    "CumulativeVarianceExplained": 0.184160735,
    "Mask": "combined",
    "Method": "aCompCor",
    "Retained": true,
    "SingularValue": 144.3608674909,
    "VarianceExplained": 0.0084458996
  },
  "a_comp_cor_104": {
    "CumulativeVarianceExplained": 0.1925222271,
    "Mask": "combined",
    "Method": "aCompCor",
    "Retained": true,
    "SingularValue": 143.6376918939,
    "VarianceExplained": 0.0083614921
  },
  "a_comp_cor_105": {
    "CumulativeVarianceExplained": 0.2007630515,
    "Mask": "combined",
    "Method": "aCompCor",
    "Retained": true,
    "SingularValue": 142.5974812955,
    "VarianceExplained": 0.0082408244
  },
  "a_comp_cor_106": {
    "CumulativeVarianceExplained": 0.208687185,
    "Mask": "combined",
    "Method": "aCompCor",
    "Retained": true,
    "SingularValue": 139.8306634875,
    "VarianceExplained": 0.0079241335
  },
  "a_comp_cor_107": {
    "CumulativeVarianceExplained": 0.216541894,
    "Mask": "combined",
    "Method": "aCompCor",
    "Retained": true,
    "SingularValue": 139.2167770085,
    "VarianceExplained": 0.007854709
  },
  "a_comp_cor_108": {
    "CumulativeVarianceExplained": 0.2243102222,
    "Mask": "combined",
    "Method": "aCompCor",
    "Retained": true,
    "SingularValue": 138.4491550201,
    "VarianceExplained": 0.0077683282
  },
  "a_comp_cor_109": {
    "CumulativeVarianceExplained": 0.2320171334,
    "Mask": "combined",
    "Method": "aCompCor",
    "Retained": true,
    "SingularValue": 137.9007734224,
    "VarianceExplained": 0.0077069111
  },
  "a_comp_cor_11": {
    "CumulativeVarianceExplained": 0.3029750837,
    "Mask": "CSF",
    "Method": "aCompCor",
    "Retained": true,
    "SingularValue": 36.3850006854,
    "VarianceExplained": 0.0124573573
  },
  "a_comp_cor_110": {
    "CumulativeVarianceExplained": 0.2396408575,
    "Mask": "combined",
    "Method": "aCompCor",
    "Retained": true,
    "SingularValue": 137.1545158678,
    "VarianceExplained": 0.0076237241
  },
  "a_comp_cor_111": {
    "CumulativeVarianceExplained": 0.2472489175,
    "Mask": "combined",
    "Method": "aCompCor",
    "Retained": true,
    "SingularValue": 137.0135412932,
    "VarianceExplained": 0.00760806
  },
  "a_comp_cor_112": {
    "CumulativeVarianceExplained": 0.2548086376,
    "Mask": "combined",
    "Method": "aCompCor",
    "Retained": true,
    "SingularValue": 136.5775710313,
    "VarianceExplained": 0.0075597201
  },
  "a_comp_cor_113": {
    "CumulativeVarianceExplained": 0.2623101678,
    "Mask": "combined",
    "Method": "aCompCor",
    "Retained": true,
    "SingularValue": 136.0509116834,
    "VarianceExplained": 0.0075015302
  },
  "a_comp_cor_114": {
    "CumulativeVarianceExplained": 0.2698068734,
    "Mask": "combined",
    "Method": "aCompCor",
    "Retained": true,
    "SingularValue": 136.0071541588,
    "VarianceExplained": 0.0074967056
  },
  "a_comp_cor_115": {
    "CumulativeVarianceExplained": 0.2772579158,
    "Mask": "combined",
    "Method": "aCompCor",
    "Retained": true,
    "SingularValue": 135.5923051547,
    "VarianceExplained": 0.0074510424
  },
  "a_comp_cor_116": {
    "CumulativeVarianceExplained": 0.2846853068,
    "Mask": "combined",
    "Method": "aCompCor",
    "Retained": true,
    "SingularValue": 135.3769327712,
    "VarianceExplained": 0.007427391
  },
  "a_comp_cor_117": {
    "CumulativeVarianceExplained": 0.2920798558,
    "Mask": "combined",
    "Method": "aCompCor",
    "Retained": true,
    "SingularValue": 135.0772993591,
    "VarianceExplained": 0.0073945489
  },
  "a_comp_cor_118": {
    "CumulativeVarianceExplained": 0.2994439763,
    "Mask": "combined",
    "Method": "aCompCor",
    "Retained": true,
    "SingularValue": 134.7990928552,
    "VarianceExplained": 0.0073641205
  },
  "a_comp_cor_119": {
    "CumulativeVarianceExplained": 0.3067343389,
    "Mask": "combined",
    "Method": "aCompCor",
    "Retained": true,
    "SingularValue": 134.1223303928,
    "VarianceExplained": 0.0072903626
  },
  "a_comp_cor_12": {
    "CumulativeVarianceExplained": 0.3150577833,
    "Mask": "CSF",
    "Method": "aCompCor",
    "Retained": true,
    "SingularValue": 35.8336804654,
    "VarianceExplained": 0.0120826996
  },
  "a_comp_cor_120": {
    "CumulativeVarianceExplained": 0.3139923006,
    "Mask": "combined",
    "Method": "aCompCor",
    "Retained": true,
    "SingularValue": 133.8239553558,
    "VarianceExplained": 0.0072579617
  },
  "a_comp_cor_121": {
    "CumulativeVarianceExplained": 0.3212348956,
    "Mask": "combined",
    "Method": "aCompCor",
    "Retained": true,
    "SingularValue": 133.6822127294,
    "VarianceExplained": 0.007242595
  },
  "a_comp_cor_122": {
    "CumulativeVarianceExplained": 0.3284116465,
    "Mask": "combined",
    "Method": "aCompCor",
    "Retained": true,
    "SingularValue": 133.0731580383,
    "VarianceExplained": 0.0071767509
  },
  "a_comp_cor_123": {
    "CumulativeVarianceExplained": 0.3355822236,
    "Mask": "combined",
    "Method": "aCompCor",
    "Retained": true,
    "SingularValue": 133.0159073435,
    "VarianceExplained": 0.0071705771
  },
  "a_comp_cor_124": {
    "CumulativeVarianceExplained": 0.34272306,
    "Mask": "combined",
    "Method": "aCompCor",
    "Retained": true,
    "SingularValue": 132.7397721191,
    "VarianceExplained": 0.0071408364
  },
  "a_comp_cor_125": {
    "CumulativeVarianceExplained": 0.3498425756,
    "Mask": "combined",
    "Method": "aCompCor",
    "Retained": true,
    "SingularValue": 132.5414591747,
    "VarianceExplained": 0.0071195156
  },
  "a_comp_cor_126": {
    "CumulativeVarianceExplained": 0.3569400827,
    "Mask": "combined",
    "Method": "aCompCor",
    "Retained": true,
    "SingularValue": 132.3364390519,
    "VarianceExplained": 0.0070975071
  },
  "a_comp_cor_127": {
    "CumulativeVarianceExplained": 0.3640134735,
    "Mask": "combined",
    "Method": "aCompCor",
    "Retained": true,
    "SingularValue": 132.111417718,
    "VarianceExplained": 0.0070733908
  },
  "a_comp_cor_128": {
    "CumulativeVarianceExplained": 0.3710692454,
    "Mask": "combined",
    "Method": "aCompCor",
    "Retained": true,
    "SingularValue": 131.9467786211,
    "VarianceExplained": 0.0070557719
  },
  "a_comp_cor_129": {
    "CumulativeVarianceExplained": 0.378085557,
    "Mask": "combined",
    "Method": "aCompCor",
    "Retained": true,
    "SingularValue": 131.5772967302,
    "VarianceExplained": 0.0070163116
  },
  "a_comp_cor_13": {
    "CumulativeVarianceExplained": 0.3269599038,
    "Mask": "CSF",
    "Method": "aCompCor",
    "Retained": true,
    "SingularValue": 35.5649005029,
    "VarianceExplained": 0.0119021205
  },
  "a_comp_cor_130": {
    "CumulativeVarianceExplained": 0.3850942819,
    "Mask": "combined",
    "Method": "aCompCor",
    "Retained": true,
    "SingularValue": 131.5061409088,
    "VarianceExplained": 0.0070087249
  },
  "a_comp_cor_131": {
    "CumulativeVarianceExplained": 0.3920837148,
    "Mask": "combined",
    "Method": "aCompCor",
    "Retained": true,
    "SingularValue": 131.3250263219,
    "VarianceExplained": 0.0069894329
  },
  "a_comp_cor_132": {
    "CumulativeVarianceExplained": 0.3990647492,
    "Mask": "combined",
    "Method": "aCompCor",
    "Retained": true,
    "SingularValue": 131.2461017942,
    "VarianceExplained": 0.0069810343
  },
  "a_comp_cor_133": {
    "CumulativeVarianceExplained": 0.4060138643,
    "Mask": "combined",
    "Method": "aCompCor",
    "Retained": true,
    "SingularValue": 130.9457109018,
    "VarianceExplained": 0.0069491151
  },
  "a_comp_cor_134": {
    "CumulativeVarianceExplained": 0.4129267802,
    "Mask": "combined",
    "Method": "aCompCor",
    "Retained": true,
    "SingularValue": 130.6042059953,
    "VarianceExplained": 0.0069129159
  },
  "a_comp_cor_135": {
    "CumulativeVarianceExplained": 0.4198168771,
    "Mask": "combined",
    "Method": "aCompCor",
    "Retained": true,
    "SingularValue": 130.3884706159,
    "VarianceExplained": 0.0068900969
  },
  "a_comp_cor_136": {
    "CumulativeVarianceExplained": 0.4266994934,
    "Mask": "combined",
    "Method": "aCompCor",
    "Retained": true,
    "SingularValue": 130.3176694626,
    "VarianceExplained": 0.0068826163
  },
  "a_comp_cor_137": {
    "CumulativeVarianceExplained": 0.4335677693,
    "Mask": "combined",
    "Method": "aCompCor",
    "Retained": true,
    "SingularValue": 130.1818362826,
    "VarianceExplained": 0.0068682759
  },
  "a_comp_cor_138": {
    "CumulativeVarianceExplained": 0.4404147299,
    "Mask": "combined",
    "Method": "aCompCor",
    "Retained": true,
    "SingularValue": 129.9796733797,
    "VarianceExplained": 0.0068469606
  },
  "a_comp_cor_139": {
    "CumulativeVarianceExplained": 0.4472404579,
    "Mask": "combined",
    "Method": "aCompCor",
    "Retained": true,
    "SingularValue": 129.7779811368,
    "VarianceExplained": 0.006825728
  },
  "a_comp_cor_14": {
    "CumulativeVarianceExplained": 0.3384714708,
    "Mask": "CSF",
    "Method": "aCompCor",
    "Retained": true,
    "SingularValue": 34.9765242525,
    "VarianceExplained": 0.011511567
  },
  "a_comp_cor_140": {
    "CumulativeVarianceExplained": 0.4540381748,
    "Mask": "combined",
    "Method": "aCompCor",
    "Retained": true,
    "SingularValue": 129.5114188383,
    "VarianceExplained": 0.0067977169
  },
  "a_comp_cor_141": {
    "CumulativeVarianceExplained": 0.4608174281,
    "Mask": "combined",
    "Method": "aCompCor",
    "Retained": true,
    "SingularValue": 129.3354144425,
    "VarianceExplained": 0.0067792534
  },
  "a_comp_cor_142": {
    "CumulativeVarianceExplained": 0.4675806885,
    "Mask": "combined",
    "Method": "aCompCor",
    "Retained": true,
    "SingularValue": 129.1827662233,
    "VarianceExplained": 0.0067632604
  },
  "a_comp_cor_143": {
    "CumulativeVarianceExplained": 0.4743222504,
    "Mask": "combined",
    "Method": "aCompCor",
    "Retained": true,
    "SingularValue": 128.9753720714,
    "VarianceExplained": 0.0067415619
  },
  "a_comp_cor_144": {
    "CumulativeVarianceExplained": 0.4810534647,
    "Mask": "combined",
    "Method": "aCompCor",
    "Retained": true,
    "SingularValue": 128.8763516988,
    "VarianceExplained": 0.0067312143
  },
  "a_comp_cor_145": {
    "CumulativeVarianceExplained": 0.4877461953,
    "Mask": "combined",
    "Method": "aCompCor",
    "Retained": true,
    "SingularValue": 128.5074180689,
    "VarianceExplained": 0.0066927306
  },
  "a_comp_cor_146": {
    "CumulativeVarianceExplained": 0.4944247417,
    "Mask": "combined",
    "Method": "aCompCor",
    "Retained": true,
    "SingularValue": 128.3711702355,
    "VarianceExplained": 0.0066785464
  },
  "a_comp_cor_147": {
    "CumulativeVarianceExplained": 0.5010785043,
    "Mask": "combined",
    "Method": "aCompCor",
    "Retained": true,
    "SingularValue": 128.1327587606,
    "VarianceExplained": 0.0066537626
  },
  "a_comp_cor_15": {
    "CumulativeVarianceExplained": 0.3494323272,
    "Mask": "CSF",
    "Method": "aCompCor",
    "Retained": true,
    "SingularValue": 34.129637219,
    "VarianceExplained": 0.0109608565
  },
  "a_comp_cor_16": {
    "CumulativeVarianceExplained": 0.3602245913,
    "Mask": "CSF",
    "Method": "aCompCor",
    "Retained": true,
    "SingularValue": 33.8661407986,
    "VarianceExplained": 0.0107922641
  },
  "a_comp_cor_17": {
    "CumulativeVarianceExplained": 0.3707551496,
    "Mask": "CSF",
    "Method": "aCompCor",
    "Retained": true,
    "SingularValue": 33.4530041334,
    "VarianceExplained": 0.0105305582
  },
  "a_comp_cor_18": {
    "CumulativeVarianceExplained": 0.3811366406,
    "Mask": "CSF",
    "Method": "aCompCor",
    "Retained": true,
    "SingularValue": 33.2153851883,
    "VarianceExplained": 0.010381491
  },
  "a_comp_cor_19": {
    "CumulativeVarianceExplained": 0.3912306006,
    "Mask": "CSF",
    "Method": "aCompCor",
    "Retained": true,
    "SingularValue": 32.7521803745,
    "VarianceExplained": 0.01009396
  },
  "a_comp_cor_20": {
    "CumulativeVarianceExplained": 0.4011297703,
    "Mask": "CSF",
    "Method": "aCompCor",
    "Retained": true,
    "SingularValue": 32.4346197929,
    "VarianceExplained": 0.0098991697
  },
  "a_comp_cor_21": {
    "CumulativeVarianceExplained": 0.4109256859,
    "Mask": "CSF",
    "Method": "aCompCor",
    "Retained": true,
    "SingularValue": 32.2650203504,
    "VarianceExplained": 0.0097959156
  },
  "a_comp_cor_22": {
    "CumulativeVarianceExplained": 0.4203414878,
    "Mask": "CSF",
    "Method": "aCompCor",
    "Retained": true,
    "SingularValue": 31.6328327349,
    "VarianceExplained": 0.009415802
  },
  "a_comp_cor_23": {
    "CumulativeVarianceExplained": 0.4296762876,
    "Mask": "CSF",
    "Method": "aCompCor",
    "Retained": true,
    "SingularValue": 31.4964734024,
    "VarianceExplained": 0.0093347997
  },
  "a_comp_cor_24": {
    "CumulativeVarianceExplained": 0.438816289,
    "Mask": "CSF",
    "Method": "aCompCor",
    "Retained": true,
    "SingularValue": 31.1661070349,
    "VarianceExplained": 0.0091400014
  },
  "a_comp_cor_25": {
    "CumulativeVarianceExplained": 0.4478059466,
    "Mask": "CSF",
    "Method": "aCompCor",
    "Retained": true,
    "SingularValue": 30.908718758,
    "VarianceExplained": 0.0089896576
  },
  "a_comp_cor_26": {
    "CumulativeVarianceExplained": 0.4567016743,
    "Mask": "CSF",
    "Method": "aCompCor",
    "Retained": true,
    "SingularValue": 30.7468173297,
    "VarianceExplained": 0.0088957277
  },
  "a_comp_cor_27": {
    "CumulativeVarianceExplained": 0.4654016647,
    "Mask": "CSF",
    "Method": "aCompCor",
    "Retained": true,
    "SingularValue": 30.4066666879,
    "VarianceExplained": 0.0086999904
  },
  "a_comp_cor_28": {
    "CumulativeVarianceExplained": 0.4740648071,
    "Mask": "CSF",
    "Method": "aCompCor",
    "Retained": true,
    "SingularValue": 30.3422060182,
    "VarianceExplained": 0.0086631424
  },
  "a_comp_cor_29": {
    "CumulativeVarianceExplained": 0.4826279114,
    "Mask": "CSF",
    "Method": "aCompCor",
    "Retained": true,
    "SingularValue": 30.1665082705,
    "VarianceExplained": 0.0085631043
  },
  "a_comp_cor_30": {
    "CumulativeVarianceExplained": 0.4911572565,
    "Mask": "CSF",
    "Method": "aCompCor",
    "Retained": true,
    "SingularValue": 30.1069852966,
    "VarianceExplained": 0.0085293451
  },
  "a_comp_cor_31": {
    "CumulativeVarianceExplained": 0.4994218986,
    "Mask": "CSF",
    "Method": "aCompCor",
    "Retained": true,
    "SingularValue": 29.6361273716,
    "VarianceExplained": 0.0082646421
  },
  "a_comp_cor_32": {
    "CumulativeVarianceExplained": 0.5076090791,
    "Mask": "CSF",
    "Method": "aCompCor",
    "Retained": true,
    "SingularValue": 29.4969158722,
    "VarianceExplained": 0.0081871805
  },
  "a_comp_cor_33": {
    "CumulativeVarianceExplained": 0.0323690909,
    "Mask": "WM",
    "Method": "aCompCor",
    "Retained": true,
    "SingularValue": 277.7091398377,
    "VarianceExplained": 0.0323690909
  },
  "a_comp_cor_34": {
    "CumulativeVarianceExplained": 0.0560998974,
    "Mask": "WM",
    "Method": "aCompCor",
    "Retained": true,
    "SingularValue": 237.7832022234,
    "VarianceExplained": 0.0237308065
  },
  "a_comp_cor_35": {
    "CumulativeVarianceExplained": 0.0764955709,
    "Mask": "WM",
    "Method": "aCompCor",
    "Retained": true,
    "SingularValue": 220.4417996779,
    "VarianceExplained": 0.0203956735
  },
  "a_comp_cor_36": {
    "CumulativeVarianceExplained": 0.0927337235,
    "Mask": "WM",
    "Method": "aCompCor",
    "Retained": true,
    "SingularValue": 196.6949596425,
    "VarianceExplained": 0.0162381526
  },
  "a_comp_cor_37": {
    "CumulativeVarianceExplained": 0.1051745559,
    "Mask": "WM",
    "Method": "aCompCor",
    "Retained": true,
    "SingularValue": 172.1668932842,
    "VarianceExplained": 0.0124408324
  },
  "a_comp_cor_38": {
    "CumulativeVarianceExplained": 0.1174203212,
    "Mask": "WM",
    "Method": "aCompCor",
    "Retained": true,
    "SingularValue": 170.811807299,
    "VarianceExplained": 0.0122457653
  },
  "a_comp_cor_39": {
    "CumulativeVarianceExplained": 0.1276042335,
    "Mask": "WM",
    "Method": "aCompCor",
    "Retained": true,
    "SingularValue": 155.7694362029,
    "VarianceExplained": 0.0101839123
  },
  "a_comp_cor_40": {
    "CumulativeVarianceExplained": 0.1371520064,
    "Mask": "WM",
    "Method": "aCompCor",
    "Retained": true,
    "SingularValue": 150.8259127542,
    "VarianceExplained": 0.0095477729
  },
  "a_comp_cor_41": {
    "CumulativeVarianceExplained": 0.1463879913,
    "Mask": "WM",
    "Method": "aCompCor",
    "Retained": true,
    "SingularValue": 148.3428194791,
    "VarianceExplained": 0.0092359849
  },
  "a_comp_cor_42": {
    "CumulativeVarianceExplained": 0.1553441526,
    "Mask": "WM",
    "Method": "aCompCor",
    "Retained": true,
    "SingularValue": 146.0783567566,
    "VarianceExplained": 0.0089561613
  },
  "a_comp_cor_43": {
    "CumulativeVarianceExplained": 0.1640622478,
    "Mask": "WM",
    "Method": "aCompCor",
    "Retained": true,
    "SingularValue": 144.1238073475,
    "VarianceExplained": 0.0087180952
  },
  "a_comp_cor_44": {
    "CumulativeVarianceExplained": 0.1726748497,
    "Mask": "WM",
    "Method": "aCompCor",
    "Retained": true,
    "SingularValue": 143.2491682122,
    "VarianceExplained": 0.0086126019
  },
  "a_comp_cor_45": {
    "CumulativeVarianceExplained": 0.1811171188,
    "Mask": "WM",
    "Method": "aCompCor",
    "Retained": true,
    "SingularValue": 141.8255639782,
    "VarianceExplained": 0.0084422692
  },
  "a_comp_cor_46": {
    "CumulativeVarianceExplained": 0.1894516899,
    "Mask": "WM",
    "Method": "aCompCor",
    "Retained": true,
    "SingularValue": 140.9180250448,
    "VarianceExplained": 0.008334571
  },
  "a_comp_cor_47": {
    "CumulativeVarianceExplained": 0.197627299,
    "Mask": "WM",
    "Method": "aCompCor",
    "Retained": true,
    "SingularValue": 139.5677194735,
    "VarianceExplained": 0.0081756091
  },
  "a_comp_cor_48": {
    "CumulativeVarianceExplained": 0.2055763292,
    "Mask": "WM",
    "Method": "aCompCor",
    "Retained": true,
    "SingularValue": 137.620140395,
    "VarianceExplained": 0.0079490302
  },
  "a_comp_cor_49": {
    "CumulativeVarianceExplained": 0.2133917903,
    "Mask": "WM",
    "Method": "aCompCor",
    "Retained": true,
    "SingularValue": 136.459012743,
    "VarianceExplained": 0.0078154611
  },
  "a_comp_cor_50": {
    "CumulativeVarianceExplained": 0.221170092,
    "Mask": "WM",
    "Method": "aCompCor",
    "Retained": true,
    "SingularValue": 136.1342225719,
    "VarianceExplained": 0.0077783017
  },
  "a_comp_cor_51": {
    "CumulativeVarianceExplained": 0.2288967456,
    "Mask": "WM",
    "Method": "aCompCor",
    "Retained": true,
    "SingularValue": 135.6815021322,
    "VarianceExplained": 0.0077266536
  },
  "a_comp_cor_52": {
    "CumulativeVarianceExplained": 0.2365467113,
    "Mask": "WM",
    "Method": "aCompCor",
    "Retained": true,
    "SingularValue": 135.0064963635,
    "VarianceExplained": 0.0076499657
  },
  "a_comp_cor_53": {
    "CumulativeVarianceExplained": 0.2441857647,
    "Mask": "WM",
    "Method": "aCompCor",
    "Retained": true,
    "SingularValue": 134.9101711982,
    "VarianceExplained": 0.0076390533
  },
  "a_comp_cor_54": {
    "CumulativeVarianceExplained": 0.2517476629,
    "Mask": "WM",
    "Method": "aCompCor",
    "Retained": true,
    "SingularValue": 134.2271397769,
    "VarianceExplained": 0.0075618982
  },
  "a_comp_cor_55": {
    "CumulativeVarianceExplained": 0.2592886704,
    "Mask": "WM",
    "Method": "aCompCor",
    "Retained": true,
    "SingularValue": 134.0416014606,
    "VarianceExplained": 0.0075410075
  },
  "a_comp_cor_56": {
    "CumulativeVarianceExplained": 0.2667836569,
    "Mask": "WM",
    "Method": "aCompCor",
    "Retained": true,
    "SingularValue": 133.6319641422,
    "VarianceExplained": 0.0074949866
  },
  "a_comp_cor_57": {
    "CumulativeVarianceExplained": 0.2742657813,
    "Mask": "WM",
    "Method": "aCompCor",
    "Retained": true,
    "SingularValue": 133.5172516775,
    "VarianceExplained": 0.0074821244
  },
  "a_comp_cor_58": {
    "CumulativeVarianceExplained": 0.2817093056,
    "Mask": "WM",
    "Method": "aCompCor",
    "Retained": true,
    "SingularValue": 133.172399893,
    "VarianceExplained": 0.0074435243
  },
  "a_comp_cor_59": {
    "CumulativeVarianceExplained": 0.289124386,
    "Mask": "WM",
    "Method": "aCompCor",
    "Retained": true,
    "SingularValue": 132.9177115419,
    "VarianceExplained": 0.0074150804
  },
  "a_comp_cor_60": {
    "CumulativeVarianceExplained": 0.2965038868,
    "Mask": "WM",
    "Method": "aCompCor",
    "Retained": true,
    "SingularValue": 132.598439432,
    "VarianceExplained": 0.0073795007
  },
  "a_comp_cor_61": {
    "CumulativeVarianceExplained": 0.3038476264,
    "Mask": "WM",
    "Method": "aCompCor",
    "Retained": true,
    "SingularValue": 132.2767628644,
    "VarianceExplained": 0.0073437396
  },
  "a_comp_cor_62": {
    "CumulativeVarianceExplained": 0.311153118,
    "Mask": "WM",
    "Method": "aCompCor",
    "Retained": true,
    "SingularValue": 131.9318478433,
    "VarianceExplained": 0.0073054916
  },
  "a_comp_cor_63": {
    "CumulativeVarianceExplained": 0.3183883225,
    "Mask": "WM",
    "Method": "aCompCor",
    "Retained": true,
    "SingularValue": 131.2956465542,
    "VarianceExplained": 0.0072352045
  },
  "a_comp_cor_64": {
    "CumulativeVarianceExplained": 0.325607568,
    "Mask": "WM",
    "Method": "aCompCor",
    "Retained": true,
    "SingularValue": 131.1507649175,
    "VarianceExplained": 0.0072192455
  },
  "a_comp_cor_65": {
    "CumulativeVarianceExplained": 0.3327994739,
    "Mask": "WM",
    "Method": "aCompCor",
    "Retained": true,
    "SingularValue": 130.9021924552,
    "VarianceExplained": 0.0071919059
  },
  "a_comp_cor_66": {
    "CumulativeVarianceExplained": 0.3399706758,
    "Mask": "WM",
    "Method": "aCompCor",
    "Retained": true,
    "SingularValue": 130.7136367091,
    "VarianceExplained": 0.0071712019
  },
  "a_comp_cor_67": {
    "CumulativeVarianceExplained": 0.3471339196,
    "Mask": "WM",
    "Method": "aCompCor",
    "Retained": true,
    "SingularValue": 130.6410880188,
    "VarianceExplained": 0.0071632438
  },
  "a_comp_cor_68": {
    "CumulativeVarianceExplained": 0.3542653724,
    "Mask": "WM",
    "Method": "aCompCor",
    "Retained": true,
    "SingularValue": 130.3508682944,
    "VarianceExplained": 0.0071314528
  },
  "a_comp_cor_69": {
    "CumulativeVarianceExplained": 0.3613795297,
    "Mask": "WM",
    "Method": "aCompCor",
    "Retained": true,
    "SingularValue": 130.1927061463,
    "VarianceExplained": 0.0071141573
  },
  "a_comp_cor_70": {
    "CumulativeVarianceExplained": 0.3684666817,
    "Mask": "WM",
    "Method": "aCompCor",
    "Retained": true,
    "SingularValue": 129.9453657444,
    "VarianceExplained": 0.007087152
  },
  "a_comp_cor_71": {
    "CumulativeVarianceExplained": 0.3755306694,
    "Mask": "WM",
    "Method": "aCompCor",
    "Retained": true,
    "SingularValue": 129.7328292114,
    "VarianceExplained": 0.0070639877
  },
  "a_comp_cor_72": {
    "CumulativeVarianceExplained": 0.3825874985,
    "Mask": "WM",
    "Method": "aCompCor",
    "Retained": true,
    "SingularValue": 129.6670774447,
    "VarianceExplained": 0.0070568291
  },
  "a_comp_cor_73": {
    "CumulativeVarianceExplained": 0.3896326952,
    "Mask": "WM",
    "Method": "aCompCor",
    "Retained": true,
    "SingularValue": 129.5601626843,
    "VarianceExplained": 0.0070451967
  },
  "a_comp_cor_74": {
    "CumulativeVarianceExplained": 0.3966315749,
    "Mask": "WM",
    "Method": "aCompCor",
    "Retained": true,
    "SingularValue": 129.133578649,
    "VarianceExplained": 0.0069988797
  },
  "a_comp_cor_75": {
    "CumulativeVarianceExplained": 0.4035930975,
    "Mask": "WM",
    "Method": "aCompCor",
    "Retained": true,
    "SingularValue": 128.7884863377,
    "VarianceExplained": 0.0069615225
  },
  "a_comp_cor_76": {
    "CumulativeVarianceExplained": 0.4105402865,
    "Mask": "WM",
    "Method": "aCompCor",
    "Retained": true,
    "SingularValue": 128.655833023,
    "VarianceExplained": 0.0069471891
  },
  "a_comp_cor_77": {
    "CumulativeVarianceExplained": 0.4174717853,
    "Mask": "WM",
    "Method": "aCompCor",
    "Retained": true,
    "SingularValue": 128.5104655093,
    "VarianceExplained": 0.0069314987
  },
  "a_comp_cor_78": {
    "CumulativeVarianceExplained": 0.4243918351,
    "Mask": "WM",
    "Method": "aCompCor",
    "Retained": true,
    "SingularValue": 128.4042897658,
    "VarianceExplained": 0.0069200498
  },
  "a_comp_cor_79": {
    "CumulativeVarianceExplained": 0.4312892982,
    "Mask": "WM",
    "Method": "aCompCor",
    "Retained": true,
    "SingularValue": 128.1945655945,
    "VarianceExplained": 0.0068974631
  },
  "a_comp_cor_80": {
    "CumulativeVarianceExplained": 0.4381557429,
    "Mask": "WM",
    "Method": "aCompCor",
    "Retained": true,
    "SingularValue": 127.9059910488,
    "VarianceExplained": 0.0068664447
  },
  "a_comp_cor_81": {
    "CumulativeVarianceExplained": 0.4450061617,
    "Mask": "WM",
    "Method": "aCompCor",
    "Retained": true,
    "SingularValue": 127.7566404482,
    "VarianceExplained": 0.0068504188
  },
  "a_comp_cor_82": {
    "CumulativeVarianceExplained": 0.4518514597,
    "Mask": "WM",
    "Method": "aCompCor",
    "Retained": true,
    "SingularValue": 127.7088814178,
    "VarianceExplained": 0.006845298
  },
  "a_comp_cor_83": {
    "CumulativeVarianceExplained": 0.458661957,
    "Mask": "WM",
    "Method": "aCompCor",
    "Retained": true,
    "SingularValue": 127.3838394263,
    "VarianceExplained": 0.0068104973
  },
  "a_comp_cor_84": {
    "CumulativeVarianceExplained": 0.4654393871,
    "Mask": "WM",
    "Method": "aCompCor",
    "Retained": true,
    "SingularValue": 127.0742180712,
    "VarianceExplained": 0.0067774301
  },
  "a_comp_cor_85": {
    "CumulativeVarianceExplained": 0.4722133258,
    "Mask": "WM",
    "Method": "aCompCor",
    "Retained": true,
    "SingularValue": 127.0414828272,
    "VarianceExplained": 0.0067739387
  },
  "a_comp_cor_86": {
    "CumulativeVarianceExplained": 0.4789723077,
    "Mask": "WM",
    "Method": "aCompCor",
    "Retained": true,
    "SingularValue": 126.9011519592,
    "VarianceExplained": 0.0067589819
  },
  "a_comp_cor_87": {
    "CumulativeVarianceExplained": 0.4857113484,
    "Mask": "WM",
    "Method": "aCompCor",
    "Retained": true,
    "SingularValue": 126.7138136145,
    "VarianceExplained": 0.0067390407
  },
  "a_comp_cor_88": {
    "CumulativeVarianceExplained": 0.4924346748,
    "Mask": "WM",
    "Method": "aCompCor",
    "Retained": true,
    "SingularValue": 126.5659895036,
    "VarianceExplained": 0.0067233264
  },
  "a_comp_cor_89": {
    "CumulativeVarianceExplained": 0.4991362687,
    "Mask": "WM",
    "Method": "aCompCor",
    "Retained": true,
    "SingularValue": 126.3612686325,
    "VarianceExplained": 0.0067015939
  },
  "a_comp_cor_90": {
    "CumulativeVarianceExplained": 0.5058322961,
    "Mask": "WM",
    "Method": "aCompCor",
    "Retained": true,
    "SingularValue": 126.3087772915,
    "VarianceExplained": 0.0066960273
  },
  "a_comp_cor_91": {
    "CumulativeVarianceExplained": 0.0322506744,
    "Mask": "combined",
    "Method": "aCompCor",
    "Retained": true,
    "SingularValue": 282.0953490391,
    "VarianceExplained": 0.0322506744
  },
  "a_comp_cor_92": {
    "CumulativeVarianceExplained": 0.0568414178,
    "Mask": "combined",
    "Method": "aCompCor",
    "Retained": true,
    "SingularValue": 246.3271913329,
    "VarianceExplained": 0.0245907434
  },
  "a_comp_cor_93": {
    "CumulativeVarianceExplained": 0.0784054613,
    "Mask": "combined",
    "Method": "aCompCor",
    "Retained": true,
    "SingularValue": 230.6702712128,
    "VarianceExplained": 0.0215640436
  },
  "a_comp_cor_94": {
    "CumulativeVarianceExplained": 0.0948058986,
    "Mask": "combined",
    "Method": "aCompCor",
    "Retained": true,
    "SingularValue": 201.165842215,
    "VarianceExplained": 0.0164004373
  },
  "a_comp_cor_95": {
    "CumulativeVarianceExplained": 0.1072939854,
    "Mask": "combined",
    "Method": "aCompCor",
    "Retained": true,
    "SingularValue": 175.5393475766,
    "VarianceExplained": 0.0124880868
  },
  "a_comp_cor_96": {
    "CumulativeVarianceExplained": 0.1195280945,
    "Mask": "combined",
    "Method": "aCompCor",
    "Retained": true,
    "SingularValue": 173.7451542271,
    "VarianceExplained": 0.0122341091
  },
  "a_comp_cor_97": {
    "CumulativeVarianceExplained": 0.12975721,
    "Mask": "combined",
    "Method": "aCompCor",
    "Retained": true,
    "SingularValue": 158.8713430456,
    "VarianceExplained": 0.0102291155
  },
  "a_comp_cor_98": {
    "CumulativeVarianceExplained": 0.139447323,
    "Mask": "combined",
    "Method": "aCompCor",
    "Retained": true,
    "SingularValue": 154.6289994515,
    "VarianceExplained": 0.009690113
  },
  "a_comp_cor_99": {
    "CumulativeVarianceExplained": 0.1490441536,
    "Mask": "combined",
    "Method": "aCompCor",
    "Retained": true,
    "SingularValue": 153.8829279382,
    "VarianceExplained": 0.0095968306
  },
  "csf": {
    "Method": "Mean"
  },
  "csf_wm": {
    "Method": "Mean"
  },
  "dropped_0": {
    "CumulativeVarianceExplained": 0.5157063244,
    "Mask": "CSF",
    "Method": "aCompCor",
    "Retained": false,
    "SingularValue": 29.3344584813,
    "VarianceExplained": 0.0080972453
  },
  "dropped_1": {
    "CumulativeVarianceExplained": 0.5237358955,
    "Mask": "CSF",
    "Method": "aCompCor",
    "Retained": false,
    "SingularValue": 29.2116172762,
    "VarianceExplained": 0.0080295711
  },
  "dropped_10": {
    "CumulativeVarianceExplained": 0.5915737553,
    "Mask": "CSF",
    "Method": "aCompCor",
    "Retained": false,
    "SingularValue": 27.6382754022,
    "VarianceExplained": 0.0071879165
  },
  "dropped_100": {
    "CumulativeVarianceExplained": 0.9866813348,
    "Mask": "CSF",
    "Method": "aCompCor",
    "Retained": false,
    "SingularValue": 14.9459342238,
    "VarianceExplained": 0.0021019737
  },
  "dropped_101": {
    "CumulativeVarianceExplained": 0.9887246467,
    "Mask": "CSF",
    "Method": "aCompCor",
    "Retained": false,
    "SingularValue": 14.7359031834,
    "VarianceExplained": 0.0020433119
  },
  "dropped_102": {
    "CumulativeVarianceExplained": 0.9907037855,
    "Mask": "CSF",
    "Method": "aCompCor",
    "Retained": false,
    "SingularValue": 14.5026562843,
    "VarianceExplained": 0.0019791388
  },
  "dropped_103": {
    "CumulativeVarianceExplained": 0.9926685219,
    "Mask": "CSF",
    "Method": "aCompCor",
    "Retained": false,
    "SingularValue": 14.4497911426,
    "VarianceExplained": 0.0019647364
  },
  "dropped_104": {
    "CumulativeVarianceExplained": 0.9946053272,
    "Mask": "CSF",
    "Method": "aCompCor",
    "Retained": false,
    "SingularValue": 14.346713167,
    "VarianceExplained": 0.0019368054
  },
  "dropped_105": {
    "CumulativeVarianceExplained": 0.996448462,
    "Mask": "CSF",
    "Method": "aCompCor",
    "Retained": false,
    "SingularValue": 13.9954854684,
    "VarianceExplained": 0.0018431347
  },
  "dropped_106": {
    "CumulativeVarianceExplained": 0.998244292,
    "Mask": "CSF",
    "Method": "aCompCor",
    "Retained": false,
    "SingularValue": 13.8147187272,
    "VarianceExplained": 0.0017958301
  },
  "dropped_107": {
    "CumulativeVarianceExplained": 1.0,
    "Mask": "CSF",
    "Method": "aCompCor",
    "Retained": false,
    "SingularValue": 13.6595240514,
    "VarianceExplained": 0.001755708
  },
  "dropped_108": {
    "CumulativeVarianceExplained": 1.0,
    "Mask": "CSF",
    "Method": "aCompCor",
    "Retained": false,
    "SingularValue": 0.0,
    "VarianceExplained": 0.0
  },
  "dropped_109": {
    "CumulativeVarianceExplained": 1.0,
    "Mask": "CSF",
    "Method": "aCompCor",
    "Retained": false,
    "SingularValue": 0.0,
    "VarianceExplained": 0.0
  },
  "dropped_11": {
    "CumulativeVarianceExplained": 0.5987288472,
    "Mask": "CSF",
    "Method": "aCompCor",
    "Retained": false,
    "SingularValue": 27.5750961362,
    "VarianceExplained": 0.0071550919
  },
  "dropped_110": {
    "CumulativeVarianceExplained": 1.0,
    "Mask": "CSF",
    "Method": "aCompCor",
    "Retained": false,
    "SingularValue": 0.0,
    "VarianceExplained": 0.0
  },
  "dropped_111": {
    "CumulativeVarianceExplained": 0.5125011601,
    "Mask": "WM",
    "Method": "aCompCor",
    "Retained": false,
    "SingularValue": 126.0523228341,
    "VarianceExplained": 0.006668864
  },
  "dropped_112": {
    "CumulativeVarianceExplained": 0.5191273875,
    "Mask": "WM",
    "Method": "aCompCor",
    "Retained": false,
    "SingularValue": 125.6487264958,
    "VarianceExplained": 0.0066262274
  },
  "dropped_113": {
    "CumulativeVarianceExplained": 0.525748447,
    "Mask": "WM",
    "Method": "aCompCor",
    "Retained": false,
    "SingularValue": 125.5997192122,
    "VarianceExplained": 0.0066210595
  },
  "dropped_114": {
    "CumulativeVarianceExplained": 0.5323372209,
    "Mask": "WM",
    "Method": "aCompCor",
    "Retained": false,
    "SingularValue": 125.2931198472,
    "VarianceExplained": 0.0065887739
  },
  "dropped_115": {
    "CumulativeVarianceExplained": 0.5389082403,
    "Mask": "WM",
    "Method": "aCompCor",
    "Retained": false,
    "SingularValue": 125.1241948808,
    "VarianceExplained": 0.0065710194
  },
  "dropped_116": {
    "CumulativeVarianceExplained": 0.5454706033,
    "Mask": "WM",
    "Method": "aCompCor",
    "Retained": false,
    "SingularValue": 125.0417513993,
    "VarianceExplained": 0.006562363
  },
  "dropped_117": {
    "CumulativeVarianceExplained": 0.5520203627,
    "Mask": "WM",
    "Method": "aCompCor",
    "Retained": false,
    "SingularValue": 124.9216169821,
    "VarianceExplained": 0.0065497594
  },
  "dropped_118": {
    "CumulativeVarianceExplained": 0.5585496818,
    "Mask": "WM",
    "Method": "aCompCor",
    "Retained": false,
    "SingularValue": 124.7265383321,
    "VarianceExplained": 0.0065293191
  },
  "dropped_119": {
    "CumulativeVarianceExplained": 0.565041078,
    "Mask": "WM",
    "Method": "aCompCor",
    "Retained": false,
    "SingularValue": 124.3637987105,
    "VarianceExplained": 0.0064913962
  },
  "dropped_12": {
    "CumulativeVarianceExplained": 0.6057989557,
    "Mask": "CSF",
    "Method": "aCompCor",
    "Retained": false,
    "SingularValue": 27.4108475627,
    "VarianceExplained": 0.0070701084
  },
  "dropped_120": {
    "CumulativeVarianceExplained": 0.5715288714,
    "Mask": "WM",
    "Method": "aCompCor",
    "Retained": false,
    "SingularValue": 124.3292832974,
    "VarianceExplained": 0.0064877935
  },
  "dropped_121": {
    "CumulativeVarianceExplained": 0.5779980624,
    "Mask": "WM",
    "Method": "aCompCor",
    "Retained": false,
    "SingularValue": 124.1509106935,
    "VarianceExplained": 0.006469191
  },
  "dropped_122": {
    "CumulativeVarianceExplained": 0.5844644753,
    "Mask": "WM",
    "Method": "aCompCor",
    "Retained": false,
    "SingularValue": 124.1242499032,
    "VarianceExplained": 0.0064664129
  },
  "dropped_123": {
    "CumulativeVarianceExplained": 0.5908993962,
    "Mask": "WM",
    "Method": "aCompCor",
    "Retained": false,
    "SingularValue": 123.8216337795,
    "VarianceExplained": 0.0064349209
  },
  "dropped_124": {
    "CumulativeVarianceExplained": 0.5973096215,
    "Mask": "WM",
    "Method": "aCompCor",
    "Retained": false,
    "SingularValue": 123.5838066408,
    "VarianceExplained": 0.0064102253
  },
  "dropped_125": {
    "CumulativeVarianceExplained": 0.6037033388,
    "Mask": "WM",
    "Method": "aCompCor",
    "Retained": false,
    "SingularValue": 123.424574178,
    "VarianceExplained": 0.0063937173
  },
  "dropped_126": {
    "CumulativeVarianceExplained": 0.6100800435,
    "Mask": "WM",
    "Method": "aCompCor",
    "Retained": false,
    "SingularValue": 123.2602580767,
    "VarianceExplained": 0.0063767046
  },
  "dropped_127": {
    "CumulativeVarianceExplained": 0.6164519524,
    "Mask": "WM",
    "Method": "aCompCor",
    "Retained": false,
    "SingularValue": 123.213899204,
    "VarianceExplained": 0.0063719089
  },
  "dropped_128": {
    "CumulativeVarianceExplained": 0.6228131925,
    "Mask": "WM",
    "Method": "aCompCor",
    "Retained": false,
    "SingularValue": 123.1107051336,
    "VarianceExplained": 0.0063612402
  },
  "dropped_129": {
    "CumulativeVarianceExplained": 0.6291396172,
    "Mask": "WM",
    "Method": "aCompCor",
    "Retained": false,
    "SingularValue": 122.773346207,
    "VarianceExplained": 0.0063264247
  },
  "dropped_13": {
    "CumulativeVarianceExplained": 0.6127194124,
    "Mask": "CSF",
    "Method": "aCompCor",
    "Retained": false,
    "SingularValue": 27.1191957283,
    "VarianceExplained": 0.0069204567
  },
  "dropped_130": {
    "CumulativeVarianceExplained": 0.6354546063,
    "Mask": "WM",
    "Method": "aCompCor",
    "Retained": false,
    "SingularValue": 122.6623342207,
    "VarianceExplained": 0.0063149891
  },
  "dropped_131": {
    "CumulativeVarianceExplained": 0.6417483145,
    "Mask": "WM",
    "Method": "aCompCor",
    "Retained": false,
    "SingularValue": 122.455479293,
    "VarianceExplained": 0.0062937082
  },
  "dropped_132": {
    "CumulativeVarianceExplained": 0.6480336801,
    "Mask": "WM",
    "Method": "aCompCor",
    "Retained": false,
    "SingularValue": 122.3742933791,
    "VarianceExplained": 0.0062853657
  },
  "dropped_133": {
    "CumulativeVarianceExplained": 0.6543118834,
    "Mask": "WM",
    "Method": "aCompCor",
    "Retained": false,
    "SingularValue": 122.304548271,
    "VarianceExplained": 0.0062782032
  },
  "dropped_134": {
    "CumulativeVarianceExplained": 0.660578557,
    "Mask": "WM",
    "Method": "aCompCor",
    "Retained": false,
    "SingularValue": 122.1921937155,
    "VarianceExplained": 0.0062666737
  },
  "dropped_135": {
    "CumulativeVarianceExplained": 0.6668231686,
    "Mask": "WM",
    "Method": "aCompCor",
    "Retained": false,
    "SingularValue": 121.9769123197,
    "VarianceExplained": 0.0062446115
  },
  "dropped_136": {
    "CumulativeVarianceExplained": 0.673046322,
    "Mask": "WM",
    "Method": "aCompCor",
    "Retained": false,
    "SingularValue": 121.767159827,
    "VarianceExplained": 0.0062231534
  },
  "dropped_137": {
    "CumulativeVarianceExplained": 0.6792428642,
    "Mask": "WM",
    "Method": "aCompCor",
    "Retained": false,
    "SingularValue": 121.5065323646,
    "VarianceExplained": 0.0061965422
  },
  "dropped_138": {
    "CumulativeVarianceExplained": 0.6854296788,
    "Mask": "WM",
    "Method": "aCompCor",
    "Retained": false,
    "SingularValue": 121.4111225724,
    "VarianceExplained": 0.0061868146
  },
  "dropped_139": {
    "CumulativeVarianceExplained": 0.6916013144,
    "Mask": "WM",
    "Method": "aCompCor",
    "Retained": false,
    "SingularValue": 121.2620934673,
    "VarianceExplained": 0.0061716356
  },
  "dropped_14": {
    "CumulativeVarianceExplained": 0.6195755979,
    "Mask": "CSF",
    "Method": "aCompCor",
    "Retained": false,
    "SingularValue": 26.9929721624,
    "VarianceExplained": 0.0068561855
  },
  "dropped_140": {
    "CumulativeVarianceExplained": 0.6977578872,
    "Mask": "WM",
    "Method": "aCompCor",
    "Retained": false,
    "SingularValue": 121.1140231858,
    "VarianceExplained": 0.0061565728
  },
  "dropped_141": {
    "CumulativeVarianceExplained": 0.7038800764,
    "Mask": "WM",
    "Method": "aCompCor",
    "Retained": false,
    "SingularValue": 120.7753478498,
    "VarianceExplained": 0.0061221892
  },
  "dropped_142": {
    "CumulativeVarianceExplained": 0.7099886804,
    "Mask": "WM",
    "Method": "aCompCor",
    "Retained": false,
    "SingularValue": 120.6412718985,
    "VarianceExplained": 0.006108604
  },
  "dropped_143": {
    "CumulativeVarianceExplained": 0.7160808941,
    "Mask": "WM",
    "Method": "aCompCor",
    "Retained": false,
    "SingularValue": 120.4793138681,
    "VarianceExplained": 0.0060922137
  },
  "dropped_144": {
    "CumulativeVarianceExplained": 0.722166629,
    "Mask": "WM",
    "Method": "aCompCor",
    "Retained": false,
    "SingularValue": 120.4152350104,
    "VarianceExplained": 0.0060857349
  },
  "dropped_145": {
    "CumulativeVarianceExplained": 0.7282325558,
    "Mask": "WM",
    "Method": "aCompCor",
    "Retained": false,
    "SingularValue": 120.2191092078,
    "VarianceExplained": 0.0060659268
  },
  "dropped_146": {
    "CumulativeVarianceExplained": 0.7342788345,
    "Mask": "WM",
    "Method": "aCompCor",
    "Retained": false,
    "SingularValue": 120.0242505779,
    "VarianceExplained": 0.0060462787
  },
  "dropped_147": {
    "CumulativeVarianceExplained": 0.7403122153,
    "Mask": "WM",
    "Method": "aCompCor",
    "Retained": false,
    "SingularValue": 119.8961644342,
    "VarianceExplained": 0.0060333808
  },
  "dropped_148": {
    "CumulativeVarianceExplained": 0.7463399747,
    "Mask": "WM",
    "Method": "aCompCor",
    "Retained": false,
    "SingularValue": 119.8402971869,
    "VarianceExplained": 0.0060277594
  },
  "dropped_149": {
    "CumulativeVarianceExplained": 0.752353373,
    "Mask": "WM",
    "Method": "aCompCor",
    "Retained": false,
    "SingularValue": 119.697452978,
    "VarianceExplained": 0.0060133983
  },
  "dropped_15": {
    "CumulativeVarianceExplained": 0.6262818377,
    "Mask": "CSF",
    "Method": "aCompCor",
    "Retained": false,
    "SingularValue": 26.6961704555,
    "VarianceExplained": 0.0067062398
  },
  "dropped_150": {
    "CumulativeVarianceExplained": 0.7583492957,
    "Mask": "WM",
    "Method": "aCompCor",
    "Retained": false,
    "SingularValue": 119.5233984193,
    "VarianceExplained": 0.0059959226
  },
  "dropped_151": {
    "CumulativeVarianceExplained": 0.7643172673,
    "Mask": "WM",
    "Method": "aCompCor",
    "Retained": false,
    "SingularValue": 119.2444832421,
    "VarianceExplained": 0.0059679716
  },
  "dropped_152": {
    "CumulativeVarianceExplained": 0.7702688282,
    "Mask": "WM",
    "Method": "aCompCor",
    "Retained": false,
    "SingularValue": 119.0804221407,
    "VarianceExplained": 0.005951561
  },
  "dropped_153": {
    "CumulativeVarianceExplained": 0.7761949205,
    "Mask": "WM",
    "Method": "aCompCor",
    "Retained": false,
    "SingularValue": 118.8253566141,
    "VarianceExplained": 0.0059260923
  },
  "dropped_154": {
    "CumulativeVarianceExplained": 0.7821113833,
    "Mask": "WM",
    "Method": "aCompCor",
    "Retained": false,
    "SingularValue": 118.7287763969,
    "VarianceExplained": 0.0059164628
  },
  "dropped_155": {
    "CumulativeVarianceExplained": 0.7880161491,
    "Mask": "WM",
    "Method": "aCompCor",
    "Retained": false,
    "SingularValue": 118.6113531494,
    "VarianceExplained": 0.0059047658
  },
  "dropped_156": {
    "CumulativeVarianceExplained": 0.7939158622,
    "Mask": "WM",
    "Method": "aCompCor",
    "Retained": false,
    "SingularValue": 118.5605945313,
    "VarianceExplained": 0.0058997131
  },
  "dropped_157": {
    "CumulativeVarianceExplained": 0.7997952187,
    "Mask": "WM",
    "Method": "aCompCor",
    "Retained": false,
    "SingularValue": 118.3558744533,
    "VarianceExplained": 0.0058793565
  },
  "dropped_158": {
    "CumulativeVarianceExplained": 0.8056645694,
    "Mask": "WM",
    "Method": "aCompCor",
    "Retained": false,
    "SingularValue": 118.2551196181,
    "VarianceExplained": 0.0058693507
  },
  "dropped_159": {
    "CumulativeVarianceExplained": 0.8115099807,
    "Mask": "WM",
    "Method": "aCompCor",
    "Retained": false,
    "SingularValue": 118.0137097722,
    "VarianceExplained": 0.0058454114
  },
  "dropped_16": {
    "CumulativeVarianceExplained": 0.632947847,
    "Mask": "CSF",
    "Method": "aCompCor",
    "Retained": false,
    "SingularValue": 26.6159751846,
    "VarianceExplained": 0.0066660093
  },
  "dropped_160": {
    "CumulativeVarianceExplained": 0.817342868,
    "Mask": "WM",
    "Method": "aCompCor",
    "Retained": false,
    "SingularValue": 117.8872168021,
    "VarianceExplained": 0.0058328873
  },
  "dropped_161": {
    "CumulativeVarianceExplained": 0.8231641599,
    "Mask": "WM",
    "Method": "aCompCor",
    "Retained": false,
    "SingularValue": 117.7699824989,
    "VarianceExplained": 0.0058212919
  },
  "dropped_162": {
    "CumulativeVarianceExplained": 0.8289660475,
    "Mask": "WM",
    "Method": "aCompCor",
    "Retained": false,
    "SingularValue": 117.5735356025,
    "VarianceExplained": 0.0058018876
  },
  "dropped_163": {
    "CumulativeVarianceExplained": 0.834754184,
    "Mask": "WM",
    "Method": "aCompCor",
    "Retained": false,
    "SingularValue": 117.4341218676,
    "VarianceExplained": 0.0057881365
  },
  "dropped_164": {
    "CumulativeVarianceExplained": 0.840518754,
    "Mask": "WM",
    "Method": "aCompCor",
    "Retained": false,
    "SingularValue": 117.1948100718,
    "VarianceExplained": 0.00576457
  },
  "dropped_165": {
    "CumulativeVarianceExplained": 0.8462649364,
    "Mask": "WM",
    "Method": "aCompCor",
    "Retained": false,
    "SingularValue": 117.0077490147,
    "VarianceExplained": 0.0057461824
  },
  "dropped_166": {
    "CumulativeVarianceExplained": 0.8519951904,
    "Mask": "WM",
    "Method": "aCompCor",
    "Retained": false,
    "SingularValue": 116.8454648928,
    "VarianceExplained": 0.0057302541
  },
  "dropped_167": {
    "CumulativeVarianceExplained": 0.857711213,
    "Mask": "WM",
    "Method": "aCompCor",
    "Retained": false,
    "SingularValue": 116.7002774192,
    "VarianceExplained": 0.0057160225
  },
  "dropped_168": {
    "CumulativeVarianceExplained": 0.8634245624,
    "Mask": "WM",
    "Method": "aCompCor",
    "Retained": false,
    "SingularValue": 116.6729871041,
    "VarianceExplained": 0.0057133495
  },
  "dropped_169": {
    "CumulativeVarianceExplained": 0.869118417,
    "Mask": "WM",
    "Method": "aCompCor",
    "Retained": false,
    "SingularValue": 116.4737637016,
    "VarianceExplained": 0.0056938546
  },
  "dropped_17": {
    "CumulativeVarianceExplained": 0.639505541,
    "Mask": "CSF",
    "Method": "aCompCor",
    "Retained": false,
    "SingularValue": 26.3988496075,
    "VarianceExplained": 0.006557694
  },
  "dropped_170": {
    "CumulativeVarianceExplained": 0.8748001661,
    "Mask": "WM",
    "Method": "aCompCor",
    "Retained": false,
    "SingularValue": 116.3498821394,
    "VarianceExplained": 0.0056817491
  },
  "dropped_171": {
    "CumulativeVarianceExplained": 0.8804557687,
    "Mask": "WM",
    "Method": "aCompCor",
    "Retained": false,
    "SingularValue": 116.0818614502,
    "VarianceExplained": 0.0056556026
  },
  "dropped_172": {
    "CumulativeVarianceExplained": 0.8860895517,
    "Mask": "WM",
    "Method": "aCompCor",
    "Retained": false,
    "SingularValue": 115.8577202889,
    "VarianceExplained": 0.005633783
  },
  "dropped_173": {
    "CumulativeVarianceExplained": 0.8917125672,
    "Mask": "WM",
    "Method": "aCompCor",
    "Retained": false,
    "SingularValue": 115.746951757,
    "VarianceExplained": 0.0056230155
  },
  "dropped_174": {
    "CumulativeVarianceExplained": 0.8973115091,
    "Mask": "WM",
    "Method": "aCompCor",
    "Retained": false,
    "SingularValue": 115.4989144761,
    "VarianceExplained": 0.0055989419
  },
  "dropped_175": {
    "CumulativeVarianceExplained": 0.9028869519,
    "Mask": "WM",
    "Method": "aCompCor",
    "Retained": false,
    "SingularValue": 115.2562825362,
    "VarianceExplained": 0.0055754429
  },
  "dropped_176": {
    "CumulativeVarianceExplained": 0.908458365,
    "Mask": "WM",
    "Method": "aCompCor",
    "Retained": false,
    "SingularValue": 115.214622744,
    "VarianceExplained": 0.0055714131
  },
  "dropped_177": {
    "CumulativeVarianceExplained": 0.9140085122,
    "Mask": "WM",
    "Method": "aCompCor",
    "Retained": false,
    "SingularValue": 114.99452716,
    "VarianceExplained": 0.0055501472
  },
  "dropped_178": {
    "CumulativeVarianceExplained": 0.9195524417,
    "Mask": "WM",
    "Method": "aCompCor",
    "Retained": false,
    "SingularValue": 114.9300962418,
    "VarianceExplained": 0.0055439295
  },
  "dropped_179": {
    "CumulativeVarianceExplained": 0.9250522631,
    "Mask": "WM",
    "Method": "aCompCor",
    "Retained": false,
    "SingularValue": 114.4719858815,
    "VarianceExplained": 0.0054998214
  },
  "dropped_18": {
    "CumulativeVarianceExplained": 0.6459954923,
    "Mask": "CSF",
    "Method": "aCompCor",
    "Retained": false,
    "SingularValue": 26.2621420233,
    "VarianceExplained": 0.0064899513
  },
  "dropped_180": {
    "CumulativeVarianceExplained": 0.9305210619,
    "Mask": "WM",
    "Method": "aCompCor",
    "Retained": false,
    "SingularValue": 114.1486804318,
    "VarianceExplained": 0.0054687988
  },
  "dropped_181": {
    "CumulativeVarianceExplained": 0.9359715647,
    "Mask": "WM",
    "Method": "aCompCor",
    "Retained": false,
    "SingularValue": 113.957576433,
    "VarianceExplained": 0.0054505028
  },
  "dropped_182": {
    "CumulativeVarianceExplained": 0.941412483,
    "Mask": "WM",
    "Method": "aCompCor",
    "Retained": false,
    "SingularValue": 113.8573380897,
    "VarianceExplained": 0.0054409183
  },
  "dropped_183": {
    "CumulativeVarianceExplained": 0.9468161242,
    "Mask": "WM",
    "Method": "aCompCor",
    "Retained": false,
    "SingularValue": 113.4666350633,
    "VarianceExplained": 0.0054036412
  },
  "dropped_184": {
    "CumulativeVarianceExplained": 0.9522091359,
    "Mask": "WM",
    "Method": "aCompCor",
    "Retained": false,
    "SingularValue": 113.3549797295,
    "VarianceExplained": 0.0053930117
  },
  "dropped_185": {
    "CumulativeVarianceExplained": 0.9575684574,
    "Mask": "WM",
    "Method": "aCompCor",
    "Retained": false,
    "SingularValue": 113.000360096,
    "VarianceExplained": 0.0053593215
  },
  "dropped_186": {
    "CumulativeVarianceExplained": 0.962899316,
    "Mask": "WM",
    "Method": "aCompCor",
    "Retained": false,
    "SingularValue": 112.6998931402,
    "VarianceExplained": 0.0053308586
  },
  "dropped_187": {
    "CumulativeVarianceExplained": 0.9682255477,
    "Mask": "WM",
    "Method": "aCompCor",
    "Retained": false,
    "SingularValue": 112.6509733924,
    "VarianceExplained": 0.0053262317
  },
  "dropped_188": {
    "CumulativeVarianceExplained": 0.9735330305,
    "Mask": "WM",
    "Method": "aCompCor",
    "Retained": false,
    "SingularValue": 112.4525270739,
    "VarianceExplained": 0.0053074828
  },
  "dropped_189": {
    "CumulativeVarianceExplained": 0.9788154253,
    "Mask": "WM",
    "Method": "aCompCor",
    "Retained": false,
    "SingularValue": 112.1864357881,
    "VarianceExplained": 0.0052823948
  },
  "dropped_19": {
    "CumulativeVarianceExplained": 0.6524089815,
    "Mask": "CSF",
    "Method": "aCompCor",
    "Retained": false,
    "SingularValue": 26.1069785451,
    "VarianceExplained": 0.0064134892
  },
  "dropped_190": {
    "CumulativeVarianceExplained": 0.9840803676,
    "Mask": "WM",
    "Method": "aCompCor",
    "Retained": false,
    "SingularValue": 112.0009563806,
    "VarianceExplained": 0.0052649423
  },
  "dropped_191": {
    "CumulativeVarianceExplained": 0.9893018771,
    "Mask": "WM",
    "Method": "aCompCor",
    "Retained": false,
    "SingularValue": 111.5380266859,
    "VarianceExplained": 0.0052215095
  },
  "dropped_192": {
    "CumulativeVarianceExplained": 0.9944900266,
    "Mask": "WM",
    "Method": "aCompCor",
    "Retained": false,
    "SingularValue": 111.1811504078,
    "VarianceExplained": 0.0051881495
  },
  "dropped_193": {
    "CumulativeVarianceExplained": 0.9996551791,
    "Mask": "WM",
    "Method": "aCompCor",
    "Retained": false,
    "SingularValue": 110.9344663374,
    "VarianceExplained": 0.0051651525
  },
  "dropped_194": {
    "CumulativeVarianceExplained": 1.0,
    "Mask": "WM",
    "Method": "aCompCor",
    "Retained": false,
    "SingularValue": 28.6630032122,
    "VarianceExplained": 0.0003448209
  },
  "dropped_195": {
    "CumulativeVarianceExplained": 1.0,
    "Mask": "WM",
    "Method": "aCompCor",
    "Retained": false,
    "SingularValue": 0.0,
    "VarianceExplained": 0.0
  },
  "dropped_196": {
    "CumulativeVarianceExplained": 1.0,
    "Mask": "WM",
    "Method": "aCompCor",
    "Retained": false,
    "SingularValue": 0.0,
    "VarianceExplained": 0.0
  },
  "dropped_197": {
    "CumulativeVarianceExplained": 0.5077245559,
    "Mask": "combined",
    "Method": "aCompCor",
    "Retained": false,
    "SingularValue": 128.0584904453,
    "VarianceExplained": 0.0066460515
  },
  "dropped_198": {
    "CumulativeVarianceExplained": 0.5143601403,
    "Mask": "combined",
    "Method": "aCompCor",
    "Retained": false,
    "SingularValue": 127.9576086922,
    "VarianceExplained": 0.0066355844
  },
  "dropped_199": {
    "CumulativeVarianceExplained": 0.5209901264,
    "Mask": "combined",
    "Method": "aCompCor",
    "Retained": false,
    "SingularValue": 127.9036194813,
    "VarianceExplained": 0.0066299861
  },
  "dropped_2": {
    "CumulativeVarianceExplained": 0.5316635969,
    "Mask": "CSF",
    "Method": "aCompCor",
    "Retained": false,
    "SingularValue": 29.0257244305,
    "VarianceExplained": 0.0079277014
  },
  "dropped_20": {
    "CumulativeVarianceExplained": 0.6587292128,
    "Mask": "CSF",
    "Method": "aCompCor",
    "Retained": false,
    "SingularValue": 25.916473802,
    "VarianceExplained": 0.0063202312
  },
  "dropped_200": {
    "CumulativeVarianceExplained": 0.5275709705,
    "Mask": "combined",
    "Method": "aCompCor",
    "Retained": false,
    "SingularValue": 127.4287220485,
    "VarianceExplained": 0.0065808441
  },
  "dropped_201": {
    "CumulativeVarianceExplained": 0.5341231864,
    "Mask": "combined",
    "Method": "aCompCor",
    "Retained": false,
    "SingularValue": 127.15124798,
    "VarianceExplained": 0.0065522159
  },
  "dropped_202": {
    "CumulativeVarianceExplained": 0.5406682839,
    "Mask": "combined",
    "Method": "aCompCor",
    "Retained": false,
    "SingularValue": 127.0821592262,
    "VarianceExplained": 0.0065450975
  },
  "dropped_203": {
    "CumulativeVarianceExplained": 0.5472027068,
    "Mask": "combined",
    "Method": "aCompCor",
    "Retained": false,
    "SingularValue": 126.9784859322,
    "VarianceExplained": 0.0065344229
  },
  "dropped_204": {
    "CumulativeVarianceExplained": 0.5537351846,
    "Mask": "combined",
    "Method": "aCompCor",
    "Retained": false,
    "SingularValue": 126.9595862623,
    "VarianceExplained": 0.0065324778
  },
  "dropped_205": {
    "CumulativeVarianceExplained": 0.5602304619,
    "Mask": "combined",
    "Method": "aCompCor",
    "Retained": false,
    "SingularValue": 126.5975707713,
    "VarianceExplained": 0.0064952772
  },
  "dropped_206": {
    "CumulativeVarianceExplained": 0.5666950977,
    "Mask": "combined",
    "Method": "aCompCor",
    "Retained": false,
    "SingularValue": 126.2986063657,
    "VarianceExplained": 0.0064646358
  },
  "dropped_207": {
    "CumulativeVarianceExplained": 0.5731327959,
    "Mask": "combined",
    "Method": "aCompCor",
    "Retained": false,
    "SingularValue": 126.0351941115,
    "VarianceExplained": 0.0064376983
  },
  "dropped_208": {
    "CumulativeVarianceExplained": 0.5795600128,
    "Mask": "combined",
    "Method": "aCompCor",
    "Retained": false,
    "SingularValue": 125.9325512212,
    "VarianceExplained": 0.0064272168
  },
  "dropped_209": {
    "CumulativeVarianceExplained": 0.5859830351,
    "Mask": "combined",
    "Method": "aCompCor",
    "Retained": false,
    "SingularValue": 125.8914517526,
    "VarianceExplained": 0.0064230223
  },
  "dropped_21": {
    "CumulativeVarianceExplained": 0.6650051751,
    "Mask": "CSF",
    "Method": "aCompCor",
    "Retained": false,
    "SingularValue": 25.8255507494,
    "VarianceExplained": 0.0062759624
  },
  "dropped_210": {
    "CumulativeVarianceExplained": 0.592378461,
    "Mask": "combined",
    "Method": "aCompCor",
    "Retained": false,
    "SingularValue": 125.6207148521,
    "VarianceExplained": 0.0063954259
  },
  "dropped_211": {
    "CumulativeVarianceExplained": 0.598752558,
    "Mask": "combined",
    "Method": "aCompCor",
    "Retained": false,
    "SingularValue": 125.4110663154,
    "VarianceExplained": 0.006374097
  },
  "dropped_212": {
    "CumulativeVarianceExplained": 0.6051229463,
    "Mask": "combined",
    "Method": "aCompCor",
    "Retained": false,
    "SingularValue": 125.374576609,
    "VarianceExplained": 0.0063703883
  },
  "dropped_213": {
    "CumulativeVarianceExplained": 0.6114778215,
    "Mask": "combined",
    "Method": "aCompCor",
    "Retained": false,
    "SingularValue": 125.2218272851,
    "VarianceExplained": 0.0063548751
  },
  "dropped_214": {
    "CumulativeVarianceExplained": 0.6178094754,
    "Mask": "combined",
    "Method": "aCompCor",
    "Retained": false,
    "SingularValue": 124.9928333746,
    "VarianceExplained": 0.006331654
  },
  "dropped_215": {
    "CumulativeVarianceExplained": 0.624128866,
    "Mask": "combined",
    "Method": "aCompCor",
    "Retained": false,
    "SingularValue": 124.8717284041,
    "VarianceExplained": 0.0063193905
  },
  "dropped_216": {
    "CumulativeVarianceExplained": 0.630426514,
    "Mask": "combined",
    "Method": "aCompCor",
    "Retained": false,
    "SingularValue": 124.6567264327,
    "VarianceExplained": 0.006297648
  },
  "dropped_217": {
    "CumulativeVarianceExplained": 0.6367143586,
    "Mask": "combined",
    "Method": "aCompCor",
    "Retained": false,
    "SingularValue": 124.5596633954,
    "VarianceExplained": 0.0062878446
  },
  "dropped_218": {
    "CumulativeVarianceExplained": 0.6429896706,
    "Mask": "combined",
    "Method": "aCompCor",
    "Retained": false,
    "SingularValue": 124.4354691515,
    "VarianceExplained": 0.0062753121
  },
  "dropped_219": {
    "CumulativeVarianceExplained": 0.6492562082,
    "Mask": "combined",
    "Method": "aCompCor",
    "Retained": false,
    "SingularValue": 124.3484421479,
    "VarianceExplained": 0.0062665375
  },
  "dropped_22": {
    "CumulativeVarianceExplained": 0.6712002799,
    "Mask": "CSF",
    "Method": "aCompCor",
    "Retained": false,
    "SingularValue": 25.658647212,
    "VarianceExplained": 0.0061951048
  },
  "dropped_220": {
    "CumulativeVarianceExplained": 0.6555069325,
    "Mask": "combined",
    "Method": "aCompCor",
    "Retained": false,
    "SingularValue": 124.191450212,
    "VarianceExplained": 0.0062507243
  },
  "dropped_221": {
    "CumulativeVarianceExplained": 0.6617380399,
    "Mask": "combined",
    "Method": "aCompCor",
    "Retained": false,
    "SingularValue": 123.9964194474,
    "VarianceExplained": 0.0062311074
  },
  "dropped_222": {
    "CumulativeVarianceExplained": 0.6679643014,
    "Mask": "combined",
    "Method": "aCompCor",
    "Retained": false,
    "SingularValue": 123.948194222,
    "VarianceExplained": 0.0062262615
  },
  "dropped_223": {
    "CumulativeVarianceExplained": 0.6741756158,
    "Mask": "combined",
    "Method": "aCompCor",
    "Retained": false,
    "SingularValue": 123.7993261066,
    "VarianceExplained": 0.0062113144
  },
  "dropped_224": {
    "CumulativeVarianceExplained": 0.6803605219,
    "Mask": "combined",
    "Method": "aCompCor",
    "Retained": false,
    "SingularValue": 123.5358711004,
    "VarianceExplained": 0.0061849061
  },
  "dropped_225": {
    "CumulativeVarianceExplained": 0.6865178157,
    "Mask": "combined",
    "Method": "aCompCor",
    "Retained": false,
    "SingularValue": 123.2598014515,
    "VarianceExplained": 0.0061572938
  },
  "dropped_226": {
    "CumulativeVarianceExplained": 0.6926694898,
    "Mask": "combined",
    "Method": "aCompCor",
    "Retained": false,
    "SingularValue": 123.2035402544,
    "VarianceExplained": 0.0061516741
  },
  "dropped_227": {
    "CumulativeVarianceExplained": 0.6987981586,
    "Mask": "combined",
    "Method": "aCompCor",
    "Retained": false,
    "SingularValue": 122.9729533048,
    "VarianceExplained": 0.0061286688
  },
  "dropped_228": {
    "CumulativeVarianceExplained": 0.7048921866,
    "Mask": "combined",
    "Method": "aCompCor",
    "Retained": false,
    "SingularValue": 122.6249225656,
    "VarianceExplained": 0.0060940279
  },
  "dropped_229": {
    "CumulativeVarianceExplained": 0.7109708019,
    "Mask": "combined",
    "Method": "aCompCor",
    "Retained": false,
    "SingularValue": 122.4697574724,
    "VarianceExplained": 0.0060786154
  },
  "dropped_23": {
    "CumulativeVarianceExplained": 0.6773619522,
    "Mask": "CSF",
    "Method": "aCompCor",
    "Retained": false,
    "SingularValue": 25.5893188377,
    "VarianceExplained": 0.0061616723
  },
  "dropped_230": {
    "CumulativeVarianceExplained": 0.7170402078,
    "Mask": "combined",
    "Method": "aCompCor",
    "Retained": false,
    "SingularValue": 122.37694684,
    "VarianceExplained": 0.0060694058
  },
  "dropped_231": {
    "CumulativeVarianceExplained": 0.7230895237,
    "Mask": "combined",
    "Method": "aCompCor",
    "Retained": false,
    "SingularValue": 122.1742436625,
    "VarianceExplained": 0.0060493159
  },
  "dropped_232": {
    "CumulativeVarianceExplained": 0.729126192,
    "Mask": "combined",
    "Method": "aCompCor",
    "Retained": false,
    "SingularValue": 122.0464584074,
    "VarianceExplained": 0.0060366683
  },
  "dropped_233": {
    "CumulativeVarianceExplained": 0.7351575387,
    "Mask": "combined",
    "Method": "aCompCor",
    "Retained": false,
    "SingularValue": 121.9926523046,
    "VarianceExplained": 0.0060313467
  },
  "dropped_234": {
    "CumulativeVarianceExplained": 0.741173851,
    "Mask": "combined",
    "Method": "aCompCor",
    "Retained": false,
    "SingularValue": 121.8405113225,
    "VarianceExplained": 0.0060163123
  },
  "dropped_235": {
    "CumulativeVarianceExplained": 0.7471686053,
    "Mask": "combined",
    "Method": "aCompCor",
    "Retained": false,
    "SingularValue": 121.622021564,
    "VarianceExplained": 0.0059947542
  },
  "dropped_236": {
    "CumulativeVarianceExplained": 0.7531437618,
    "Mask": "combined",
    "Method": "aCompCor",
    "Retained": false,
    "SingularValue": 121.4230588282,
    "VarianceExplained": 0.0059751565
  },
  "dropped_237": {
    "CumulativeVarianceExplained": 0.759108384,
    "Mask": "combined",
    "Method": "aCompCor",
    "Retained": false,
    "SingularValue": 121.3159764403,
    "VarianceExplained": 0.0059646223
  },
  "dropped_238": {
    "CumulativeVarianceExplained": 0.7650631567,
    "Mask": "combined",
    "Method": "aCompCor",
    "Retained": false,
    "SingularValue": 121.2157687726,
    "VarianceExplained": 0.0059547727
  },
  "dropped_239": {
    "CumulativeVarianceExplained": 0.7710018647,
    "Mask": "combined",
    "Method": "aCompCor",
    "Retained": false,
    "SingularValue": 121.0521514022,
    "VarianceExplained": 0.005938708
  },
  "dropped_24": {
    "CumulativeVarianceExplained": 0.6835057802,
    "Mask": "CSF",
    "Method": "aCompCor",
    "Retained": false,
    "SingularValue": 25.552238414,
    "VarianceExplained": 0.006143828
  },
  "dropped_240": {
    "CumulativeVarianceExplained": 0.7769033859,
    "Mask": "combined",
    "Method": "aCompCor",
    "Retained": false,
    "SingularValue": 120.6725555844,
    "VarianceExplained": 0.0059015212
  },
  "dropped_241": {
    "CumulativeVarianceExplained": 0.7827896142,
    "Mask": "combined",
    "Method": "aCompCor",
    "Retained": false,
    "SingularValue": 120.5161025938,
    "VarianceExplained": 0.0058862283
  },
  "dropped_242": {
    "CumulativeVarianceExplained": 0.7886642371,
    "Mask": "combined",
    "Method": "aCompCor",
    "Retained": false,
    "SingularValue": 120.3972372978,
    "VarianceExplained": 0.0058746229
  },
  "dropped_243": {
    "CumulativeVarianceExplained": 0.7945234934,
    "Mask": "combined",
    "Method": "aCompCor",
    "Retained": false,
    "SingularValue": 120.2396698351,
    "VarianceExplained": 0.0058592563
  },
  "dropped_244": {
    "CumulativeVarianceExplained": 0.8003771718,
    "Mask": "combined",
    "Method": "aCompCor",
    "Retained": false,
    "SingularValue": 120.1824227531,
    "VarianceExplained": 0.0058536784
  },
  "dropped_245": {
    "CumulativeVarianceExplained": 0.80621496,
    "Mask": "combined",
    "Method": "aCompCor",
    "Retained": false,
    "SingularValue": 120.0191904101,
    "VarianceExplained": 0.0058377882
  },
  "dropped_246": {
    "CumulativeVarianceExplained": 0.8120395855,
    "Mask": "combined",
    "Method": "aCompCor",
    "Retained": false,
    "SingularValue": 119.8838077036,
    "VarianceExplained": 0.0058246255
  },
  "dropped_247": {
    "CumulativeVarianceExplained": 0.817846601,
    "Mask": "combined",
    "Method": "aCompCor",
    "Retained": false,
    "SingularValue": 119.7024441879,
    "VarianceExplained": 0.0058070155
  },
  "dropped_248": {
    "CumulativeVarianceExplained": 0.8236488544,
    "Mask": "combined",
    "Method": "aCompCor",
    "Retained": false,
    "SingularValue": 119.6533523361,
    "VarianceExplained": 0.0058022534
  },
  "dropped_249": {
    "CumulativeVarianceExplained": 0.8294326552,
    "Mask": "combined",
    "Method": "aCompCor",
    "Retained": false,
    "SingularValue": 119.4629377067,
    "VarianceExplained": 0.0057838008
  },
  "dropped_25": {
    "CumulativeVarianceExplained": 0.6896007391,
    "Mask": "CSF",
    "Method": "aCompCor",
    "Retained": false,
    "SingularValue": 25.4504120658,
    "VarianceExplained": 0.0060949589
  },
  "dropped_250": {
    "CumulativeVarianceExplained": 0.8351887697,
    "Mask": "combined",
    "Method": "aCompCor",
    "Retained": false,
    "SingularValue": 119.176667699,
    "VarianceExplained": 0.0057561145
  },
  "dropped_251": {
    "CumulativeVarianceExplained": 0.8409316264,
    "Mask": "combined",
    "Method": "aCompCor",
    "Retained": false,
    "SingularValue": 119.0393413294,
    "VarianceExplained": 0.0057428567
  },
  "dropped_252": {
    "CumulativeVarianceExplained": 0.8466527563,
    "Mask": "combined",
    "Method": "aCompCor",
    "Retained": false,
    "SingularValue": 118.8139494556,
    "VarianceExplained": 0.00572113
  },
  "dropped_253": {
    "CumulativeVarianceExplained": 0.8523576915,
    "Mask": "combined",
    "Method": "aCompCor",
    "Retained": false,
    "SingularValue": 118.645667796,
    "VarianceExplained": 0.0057049352
  },
  "dropped_254": {
    "CumulativeVarianceExplained": 0.8580540459,
    "Mask": "combined",
    "Method": "aCompCor",
    "Retained": false,
    "SingularValue": 118.5564055718,
    "VarianceExplained": 0.0056963543
  },
  "dropped_255": {
    "CumulativeVarianceExplained": 0.8637399235,
    "Mask": "combined",
    "Method": "aCompCor",
    "Retained": false,
    "SingularValue": 118.4473312719,
    "VarianceExplained": 0.0056858776
  },
  "dropped_256": {
    "CumulativeVarianceExplained": 0.8694107172,
    "Mask": "combined",
    "Method": "aCompCor",
    "Retained": false,
    "SingularValue": 118.290113834,
    "VarianceExplained": 0.0056707937
  },
  "dropped_257": {
    "CumulativeVarianceExplained": 0.8750528884,
    "Mask": "combined",
    "Method": "aCompCor",
    "Retained": false,
    "SingularValue": 117.9912099148,
    "VarianceExplained": 0.0056421712
  },
  "dropped_258": {
    "CumulativeVarianceExplained": 0.8806805518,
    "Mask": "combined",
    "Method": "aCompCor",
    "Retained": false,
    "SingularValue": 117.8394167868,
    "VarianceExplained": 0.0056276634
  },
  "dropped_259": {
    "CumulativeVarianceExplained": 0.8863014076,
    "Mask": "combined",
    "Method": "aCompCor",
    "Retained": false,
    "SingularValue": 117.7681210201,
    "VarianceExplained": 0.0056208558
  },
  "dropped_26": {
    "CumulativeVarianceExplained": 0.6956093547,
    "Mask": "CSF",
    "Method": "aCompCor",
    "Retained": false,
    "SingularValue": 25.2694993006,
    "VarianceExplained": 0.0060086156
  },
  "dropped_260": {
    "CumulativeVarianceExplained": 0.8919137511,
    "Mask": "combined",
    "Method": "aCompCor",
    "Retained": false,
    "SingularValue": 117.6789128458,
    "VarianceExplained": 0.0056123435
  },
  "dropped_261": {
    "CumulativeVarianceExplained": 0.8974940156,
    "Mask": "combined",
    "Method": "aCompCor",
    "Retained": false,
    "SingularValue": 117.342117251,
    "VarianceExplained": 0.0055802645
  },
  "dropped_262": {
    "CumulativeVarianceExplained": 0.9030450398,
    "Mask": "combined",
    "Method": "aCompCor",
    "Retained": false,
    "SingularValue": 117.0342794056,
    "VarianceExplained": 0.0055510242
  },
  "dropped_263": {
    "CumulativeVarianceExplained": 0.9085881888,
    "Mask": "combined",
    "Method": "aCompCor",
    "Retained": false,
    "SingularValue": 116.9512321783,
    "VarianceExplained": 0.005543149
  },
  "dropped_264": {
    "CumulativeVarianceExplained": 0.9141238463,
    "Mask": "combined",
    "Method": "aCompCor",
    "Retained": false,
    "SingularValue": 116.8721763754,
    "VarianceExplained": 0.0055356575
  },
  "dropped_265": {
    "CumulativeVarianceExplained": 0.919627705,
    "Mask": "combined",
    "Method": "aCompCor",
    "Retained": false,
    "SingularValue": 116.5360159937,
    "VarianceExplained": 0.0055038588
  },
  "dropped_266": {
    "CumulativeVarianceExplained": 0.9251151949,
    "Mask": "combined",
    "Method": "aCompCor",
    "Retained": false,
    "SingularValue": 116.3625937586,
    "VarianceExplained": 0.0054874899
  },
  "dropped_267": {
    "CumulativeVarianceExplained": 0.9305809205,
    "Mask": "combined",
    "Method": "aCompCor",
    "Retained": false,
    "SingularValue": 116.1316067084,
    "VarianceExplained": 0.0054657255
  },
  "dropped_268": {
    "CumulativeVarianceExplained": 0.936014803,
    "Mask": "combined",
    "Method": "aCompCor",
    "Retained": false,
    "SingularValue": 115.7928246204,
    "VarianceExplained": 0.0054338825
  },
  "dropped_269": {
    "CumulativeVarianceExplained": 0.9414444888,
    "Mask": "combined",
    "Method": "aCompCor",
    "Retained": false,
    "SingularValue": 115.7481012169,
    "VarianceExplained": 0.0054296858
  },
  "dropped_27": {
    "CumulativeVarianceExplained": 0.7015882796,
    "Mask": "CSF",
    "Method": "aCompCor",
    "Retained": false,
    "SingularValue": 25.2069890913,
    "VarianceExplained": 0.0059789248
  },
  "dropped_270": {
    "CumulativeVarianceExplained": 0.9468238736,
    "Mask": "combined",
    "Method": "aCompCor",
    "Retained": false,
    "SingularValue": 115.2107047501,
    "VarianceExplained": 0.0053793848
  },
  "dropped_271": {
    "CumulativeVarianceExplained": 0.9521773017,
    "Mask": "combined",
    "Method": "aCompCor",
    "Retained": false,
    "SingularValue": 114.9324100545,
    "VarianceExplained": 0.0053534281
  },
  "dropped_272": {
    "CumulativeVarianceExplained": 0.9575193598,
    "Mask": "combined",
    "Method": "aCompCor",
    "Retained": false,
    "SingularValue": 114.8102933499,
    "VarianceExplained": 0.005342058
  },
  "dropped_273": {
    "CumulativeVarianceExplained": 0.962840927,
    "Mask": "combined",
    "Method": "aCompCor",
    "Retained": false,
    "SingularValue": 114.5898906417,
    "VarianceExplained": 0.0053215673
  },
  "dropped_274": {
    "CumulativeVarianceExplained": 0.9681447436,
    "Mask": "combined",
    "Method": "aCompCor",
    "Retained": false,
    "SingularValue": 114.3986172332,
    "VarianceExplained": 0.0053038166
  },
  "dropped_275": {
    "CumulativeVarianceExplained": 0.9734351764,
    "Mask": "combined",
    "Method": "aCompCor",
    "Retained": false,
    "SingularValue": 114.2541872901,
    "VarianceExplained": 0.0052904328
  },
  "dropped_276": {
    "CumulativeVarianceExplained": 0.9787158589,
    "Mask": "combined",
    "Method": "aCompCor",
    "Retained": false,
    "SingularValue": 114.1488539416,
    "VarianceExplained": 0.0052806825
  },
  "dropped_277": {
    "CumulativeVarianceExplained": 0.9839548909,
    "Mask": "combined",
    "Method": "aCompCor",
    "Retained": false,
    "SingularValue": 113.6977967949,
    "VarianceExplained": 0.0052390319
  },
  "dropped_278": {
    "CumulativeVarianceExplained": 0.9891540348,
    "Mask": "combined",
    "Method": "aCompCor",
    "Retained": false,
    "SingularValue": 113.2641434649,
    "VarianceExplained": 0.0051991439
  },
  "dropped_279": {
    "CumulativeVarianceExplained": 0.9943291446,
    "Mask": "combined",
    "Method": "aCompCor",
    "Retained": false,
    "SingularValue": 113.0020464469,
    "VarianceExplained": 0.0051751098
  },
  "dropped_28": {
    "CumulativeVarianceExplained": 0.7074687475,
    "Mask": "CSF",
    "Method": "aCompCor",
    "Retained": false,
    "SingularValue": 24.9985817028,
    "VarianceExplained": 0.0058804679
  },
  "dropped_280": {
    "CumulativeVarianceExplained": 0.9994674797,
    "Mask": "combined",
    "Method": "aCompCor",
    "Retained": false,
    "SingularValue": 112.599830746,
    "VarianceExplained": 0.0051383351
  },
  "dropped_281": {
    "CumulativeVarianceExplained": 1.0,
    "Mask": "combined",
    "Method": "aCompCor",
    "Retained": false,
    "SingularValue": 36.2488830082,
    "VarianceExplained": 0.0005325203
  },
  "dropped_282": {
    "CumulativeVarianceExplained": 1.0,
    "Mask": "combined",
    "Method": "aCompCor",
    "Retained": false,
    "SingularValue": 0.0,
    "VarianceExplained": 0.0
  },
  "dropped_283": {
    "CumulativeVarianceExplained": 1.0,
    "Mask": "combined",
    "Method": "aCompCor",
    "Retained": false,
    "SingularValue": 0.0,
    "VarianceExplained": 0.0
  },
  "dropped_29": {
    "CumulativeVarianceExplained": 0.7132498496,
    "Mask": "CSF",
    "Method": "aCompCor",
    "Retained": false,
    "SingularValue": 24.7864738273,
    "VarianceExplained": 0.0057811021
  },
  "dropped_3": {
    "CumulativeVarianceExplained": 0.5394726667,
    "Mask": "CSF",
    "Method": "aCompCor",
    "Retained": false,
    "SingularValue": 28.807732729,
    "VarianceExplained": 0.0078090698
  },
  "dropped_30": {
    "CumulativeVarianceExplained": 0.7190047967,
    "Mask": "CSF",
    "Method": "aCompCor",
    "Retained": false,
    "SingularValue": 24.730340527,
    "VarianceExplained": 0.0057549471
  },
  "dropped_31": {
    "CumulativeVarianceExplained": 0.7246629122,
    "Mask": "CSF",
    "Method": "aCompCor",
    "Retained": false,
    "SingularValue": 24.5214038806,
    "VarianceExplained": 0.0056581155
  },
  "dropped_32": {
    "CumulativeVarianceExplained": 0.7302509802,
    "Mask": "CSF",
    "Method": "aCompCor",
    "Retained": false,
    "SingularValue": 24.3691435956,
    "VarianceExplained": 0.005588068
  },
  "dropped_33": {
    "CumulativeVarianceExplained": 0.7357598633,
    "Mask": "CSF",
    "Method": "aCompCor",
    "Retained": false,
    "SingularValue": 24.1958678667,
    "VarianceExplained": 0.0055088831
  },
  "dropped_34": {
    "CumulativeVarianceExplained": 0.7412019392,
    "Mask": "CSF",
    "Method": "aCompCor",
    "Retained": false,
    "SingularValue": 24.0487067072,
    "VarianceExplained": 0.0054420759
  },
  "dropped_35": {
    "CumulativeVarianceExplained": 0.7466086601,
    "Mask": "CSF",
    "Method": "aCompCor",
    "Retained": false,
    "SingularValue": 23.9704617798,
    "VarianceExplained": 0.0054067208
  },
  "dropped_36": {
    "CumulativeVarianceExplained": 0.7519548872,
    "Mask": "CSF",
    "Method": "aCompCor",
    "Retained": false,
    "SingularValue": 23.8359863962,
    "VarianceExplained": 0.0053462271
  },
  "dropped_37": {
    "CumulativeVarianceExplained": 0.7572079184,
    "Mask": "CSF",
    "Method": "aCompCor",
    "Retained": false,
    "SingularValue": 23.6273175231,
    "VarianceExplained": 0.0052530312
  },
  "dropped_38": {
    "CumulativeVarianceExplained": 0.7624413074,
    "Mask": "CSF",
    "Method": "aCompCor",
    "Retained": false,
    "SingularValue": 23.5831023466,
    "VarianceExplained": 0.005233389
  },
  "dropped_39": {
    "CumulativeVarianceExplained": 0.7675941344,
    "Mask": "CSF",
    "Method": "aCompCor",
    "Retained": false,
    "SingularValue": 23.4008811063,
    "VarianceExplained": 0.0051528271
  },
  "dropped_4": {
    "CumulativeVarianceExplained": 0.5472336922,
    "Mask": "CSF",
    "Method": "aCompCor",
    "Retained": false,
    "SingularValue": 28.7189780193,
    "VarianceExplained": 0.0077610255
  },
  "dropped_40": {
    "CumulativeVarianceExplained": 0.7726871848,
    "Mask": "CSF",
    "Method": "aCompCor",
    "Retained": false,
    "SingularValue": 23.2647512635,
    "VarianceExplained": 0.0050930504
  },
  "dropped_41": {
    "CumulativeVarianceExplained": 0.7777212011,
    "Mask": "CSF",
    "Method": "aCompCor",
    "Retained": false,
    "SingularValue": 23.1295261298,
    "VarianceExplained": 0.0050340163
  },
  "dropped_42": {
    "CumulativeVarianceExplained": 0.7826643963,
    "Mask": "CSF",
    "Method": "aCompCor",
    "Retained": false,
    "SingularValue": 22.9199310842,
    "VarianceExplained": 0.0049431952
  },
  "dropped_43": {
    "CumulativeVarianceExplained": 0.7875689544,
    "Mask": "CSF",
    "Method": "aCompCor",
    "Retained": false,
    "SingularValue": 22.8301817195,
    "VarianceExplained": 0.0049045581
  },
  "dropped_44": {
    "CumulativeVarianceExplained": 0.7924162122,
    "Mask": "CSF",
    "Method": "aCompCor",
    "Retained": false,
    "SingularValue": 22.6964265729,
    "VarianceExplained": 0.0048472578
  },
  "dropped_45": {
    "CumulativeVarianceExplained": 0.7972389489,
    "Mask": "CSF",
    "Method": "aCompCor",
    "Retained": false,
    "SingularValue": 22.6389460256,
    "VarianceExplained": 0.0048227367
  },
  "dropped_46": {
    "CumulativeVarianceExplained": 0.8019882485,
    "Mask": "CSF",
    "Method": "aCompCor",
    "Retained": false,
    "SingularValue": 22.4659200696,
    "VarianceExplained": 0.0047492996
  },
  "dropped_47": {
    "CumulativeVarianceExplained": 0.8067081831,
    "Mask": "CSF",
    "Method": "aCompCor",
    "Retained": false,
    "SingularValue": 22.3963587921,
    "VarianceExplained": 0.0047199346
  },
  "dropped_48": {
    "CumulativeVarianceExplained": 0.8114184355,
    "Mask": "CSF",
    "Method": "aCompCor",
    "Retained": false,
    "SingularValue": 22.373375896,
    "VarianceExplained": 0.0047102525
  },
  "dropped_49": {
    "CumulativeVarianceExplained": 0.8160690891,
    "Mask": "CSF",
    "Method": "aCompCor",
    "Retained": false,
    "SingularValue": 22.2313800953,
    "VarianceExplained": 0.0046506536
  },
  "dropped_5": {
    "CumulativeVarianceExplained": 0.5548029783,
    "Mask": "CSF",
    "Method": "aCompCor",
    "Retained": false,
    "SingularValue": 28.3620023168,
    "VarianceExplained": 0.0075692861
  },
  "dropped_50": {
    "CumulativeVarianceExplained": 0.8206260074,
    "Mask": "CSF",
    "Method": "aCompCor",
    "Retained": false,
    "SingularValue": 22.0061995207,
    "VarianceExplained": 0.0045569183
  },
  "dropped_51": {
    "CumulativeVarianceExplained": 0.8251618207,
    "Mask": "CSF",
    "Method": "aCompCor",
    "Retained": false,
    "SingularValue": 21.9551804132,
    "VarianceExplained": 0.0045358133
  },
  "dropped_52": {
    "CumulativeVarianceExplained": 0.8296521813,
    "Mask": "CSF",
    "Method": "aCompCor",
    "Retained": false,
    "SingularValue": 21.8448987289,
    "VarianceExplained": 0.0044903606
  },
  "dropped_53": {
    "CumulativeVarianceExplained": 0.8340717559,
    "Mask": "CSF",
    "Method": "aCompCor",
    "Retained": false,
    "SingularValue": 21.6720335962,
    "VarianceExplained": 0.0044195747
  },
  "dropped_54": {
    "CumulativeVarianceExplained": 0.8384105739,
    "Mask": "CSF",
    "Method": "aCompCor",
    "Retained": false,
    "SingularValue": 21.47311964,
    "VarianceExplained": 0.004338818
  },
  "dropped_55": {
    "CumulativeVarianceExplained": 0.842728921,
    "Mask": "CSF",
    "Method": "aCompCor",
    "Retained": false,
    "SingularValue": 21.4224035756,
    "VarianceExplained": 0.004318347
  },
  "dropped_56": {
    "CumulativeVarianceExplained": 0.8469652912,
    "Mask": "CSF",
    "Method": "aCompCor",
    "Retained": false,
    "SingularValue": 21.2180945052,
    "VarianceExplained": 0.0042363702
  },
  "dropped_57": {
    "CumulativeVarianceExplained": 0.8511720478,
    "Mask": "CSF",
    "Method": "aCompCor",
    "Retained": false,
    "SingularValue": 21.1438038603,
    "VarianceExplained": 0.0042067566
  },
  "dropped_58": {
    "CumulativeVarianceExplained": 0.8553021042,
    "Mask": "CSF",
    "Method": "aCompCor",
    "Retained": false,
    "SingularValue": 20.9501635733,
    "VarianceExplained": 0.0041300564
  },
  "dropped_59": {
    "CumulativeVarianceExplained": 0.8593761236,
    "Mask": "CSF",
    "Method": "aCompCor",
    "Retained": false,
    "SingularValue": 20.8075512304,
    "VarianceExplained": 0.0040740194
  },
  "dropped_6": {
    "CumulativeVarianceExplained": 0.5622951575,
    "Mask": "CSF",
    "Method": "aCompCor",
    "Retained": false,
    "SingularValue": 28.2171732856,
    "VarianceExplained": 0.0074921792
  },
  "dropped_60": {
    "CumulativeVarianceExplained": 0.8634162088,
    "Mask": "CSF",
    "Method": "aCompCor",
    "Retained": false,
    "SingularValue": 20.7207126282,
    "VarianceExplained": 0.0040400852
  },
  "dropped_61": {
    "CumulativeVarianceExplained": 0.8674284822,
    "Mask": "CSF",
    "Method": "aCompCor",
    "Retained": false,
    "SingularValue": 20.6492692885,
    "VarianceExplained": 0.0040122734
  },
  "dropped_62": {
    "CumulativeVarianceExplained": 0.8714179738,
    "Mask": "CSF",
    "Method": "aCompCor",
    "Retained": false,
    "SingularValue": 20.5905622049,
    "VarianceExplained": 0.0039894916
  },
  "dropped_63": {
    "CumulativeVarianceExplained": 0.8753884904,
    "Mask": "CSF",
    "Method": "aCompCor",
    "Retained": false,
    "SingularValue": 20.5415370467,
    "VarianceExplained": 0.0039705166
  },
  "dropped_64": {
    "CumulativeVarianceExplained": 0.8792224751,
    "Mask": "CSF",
    "Method": "aCompCor",
    "Retained": false,
    "SingularValue": 20.1852724003,
    "VarianceExplained": 0.0038339847
  },
  "dropped_65": {
    "CumulativeVarianceExplained": 0.8830461418,
    "Mask": "CSF",
    "Method": "aCompCor",
    "Retained": false,
    "SingularValue": 20.158092828,
    "VarianceExplained": 0.0038236667
  },
  "dropped_66": {
    "CumulativeVarianceExplained": 0.8868212586,
    "Mask": "CSF",
    "Method": "aCompCor",
    "Retained": false,
    "SingularValue": 20.0297080696,
    "VarianceExplained": 0.0037751167
  },
  "dropped_67": {
    "CumulativeVarianceExplained": 0.8905548962,
    "Mask": "CSF",
    "Method": "aCompCor",
    "Retained": false,
    "SingularValue": 19.9193659892,
    "VarianceExplained": 0.0037336377
  },
  "dropped_68": {
    "CumulativeVarianceExplained": 0.8942116333,
    "Mask": "CSF",
    "Method": "aCompCor",
    "Retained": false,
    "SingularValue": 19.7131620584,
    "VarianceExplained": 0.003656737
  },
  "dropped_69": {
    "CumulativeVarianceExplained": 0.8978157488,
    "Mask": "CSF",
    "Method": "aCompCor",
    "Retained": false,
    "SingularValue": 19.5708089918,
    "VarianceExplained": 0.0036041155
  },
  "dropped_7": {
    "CumulativeVarianceExplained": 0.5697698441,
    "Mask": "CSF",
    "Method": "aCompCor",
    "Retained": false,
    "SingularValue": 28.1842135909,
    "VarianceExplained": 0.0074746866
  },
  "dropped_70": {
    "CumulativeVarianceExplained": 0.901378128,
    "Mask": "CSF",
    "Method": "aCompCor",
    "Retained": false,
    "SingularValue": 19.4571624087,
    "VarianceExplained": 0.0035623793
  },
  "dropped_71": {
    "CumulativeVarianceExplained": 0.904894464,
    "Mask": "CSF",
    "Method": "aCompCor",
    "Retained": false,
    "SingularValue": 19.3310126656,
    "VarianceExplained": 0.0035163359
  },
  "dropped_72": {
    "CumulativeVarianceExplained": 0.9083503527,
    "Mask": "CSF",
    "Method": "aCompCor",
    "Retained": false,
    "SingularValue": 19.1641386734,
    "VarianceExplained": 0.0034558888
  },
  "dropped_73": {
    "CumulativeVarianceExplained": 0.9117580246,
    "Mask": "CSF",
    "Method": "aCompCor",
    "Retained": false,
    "SingularValue": 19.0299790542,
    "VarianceExplained": 0.0034076718
  },
  "dropped_74": {
    "CumulativeVarianceExplained": 0.9151150023,
    "Mask": "CSF",
    "Method": "aCompCor",
    "Retained": false,
    "SingularValue": 18.8878992653,
    "VarianceExplained": 0.0033569777
  },
  "dropped_75": {
    "CumulativeVarianceExplained": 0.9184286283,
    "Mask": "CSF",
    "Method": "aCompCor",
    "Retained": false,
    "SingularValue": 18.7655443543,
    "VarianceExplained": 0.0033136259
  },
  "dropped_76": {
    "CumulativeVarianceExplained": 0.9216712408,
    "Mask": "CSF",
    "Method": "aCompCor",
    "Retained": false,
    "SingularValue": 18.5633757074,
    "VarianceExplained": 0.0032426125
  },
  "dropped_77": {
    "CumulativeVarianceExplained": 0.9248761141,
    "Mask": "CSF",
    "Method": "aCompCor",
    "Retained": false,
    "SingularValue": 18.4550345183,
    "VarianceExplained": 0.0032048733
  },
  "dropped_78": {
    "CumulativeVarianceExplained": 0.9280639353,
    "Mask": "CSF",
    "Method": "aCompCor",
    "Retained": false,
    "SingularValue": 18.4058722564,
    "VarianceExplained": 0.0031878212
  },
  "dropped_79": {
    "CumulativeVarianceExplained": 0.9311786048,
    "Mask": "CSF",
    "Method": "aCompCor",
    "Retained": false,
    "SingularValue": 18.193464581,
    "VarianceExplained": 0.0031146695
  },
  "dropped_8": {
    "CumulativeVarianceExplained": 0.57713642,
    "Mask": "CSF",
    "Method": "aCompCor",
    "Retained": false,
    "SingularValue": 27.9796488784,
    "VarianceExplained": 0.0073665759
  },
  "dropped_80": {
    "CumulativeVarianceExplained": 0.9342550163,
    "Mask": "CSF",
    "Method": "aCompCor",
    "Retained": false,
    "SingularValue": 18.0813827471,
    "VarianceExplained": 0.0030764115
  },
  "dropped_81": {
    "CumulativeVarianceExplained": 0.9373079592,
    "Mask": "CSF",
    "Method": "aCompCor",
    "Retained": false,
    "SingularValue": 18.0122833579,
    "VarianceExplained": 0.0030529429
  },
  "dropped_82": {
    "CumulativeVarianceExplained": 0.9403265624,
    "Mask": "CSF",
    "Method": "aCompCor",
    "Retained": false,
    "SingularValue": 17.9106950768,
    "VarianceExplained": 0.0030186032
  },
  "dropped_83": {
    "CumulativeVarianceExplained": 0.9433024187,
    "Mask": "CSF",
    "Method": "aCompCor",
    "Retained": false,
    "SingularValue": 17.7834249786,
    "VarianceExplained": 0.0029758563
  },
  "dropped_84": {
    "CumulativeVarianceExplained": 0.9462511652,
    "Mask": "CSF",
    "Method": "aCompCor",
    "Retained": false,
    "SingularValue": 17.702236718,
    "VarianceExplained": 0.0029487465
  },
  "dropped_85": {
    "CumulativeVarianceExplained": 0.9491683414,
    "Mask": "CSF",
    "Method": "aCompCor",
    "Retained": false,
    "SingularValue": 17.6072188182,
    "VarianceExplained": 0.0029171763
  },
  "dropped_86": {
    "CumulativeVarianceExplained": 0.9520485315,
    "Mask": "CSF",
    "Method": "aCompCor",
    "Retained": false,
    "SingularValue": 17.4952439399,
    "VarianceExplained": 0.0028801901
  },
  "dropped_87": {
    "CumulativeVarianceExplained": 0.9549017355,
    "Mask": "CSF",
    "Method": "aCompCor",
    "Retained": false,
    "SingularValue": 17.4130898582,
    "VarianceExplained": 0.002853204
  },
  "dropped_88": {
    "CumulativeVarianceExplained": 0.9576518543,
    "Mask": "CSF",
    "Method": "aCompCor",
    "Retained": false,
    "SingularValue": 17.0956315745,
    "VarianceExplained": 0.0027501187
  },
  "dropped_89": {
    "CumulativeVarianceExplained": 0.9603766565,
    "Mask": "CSF",
    "Method": "aCompCor",
    "Retained": false,
    "SingularValue": 17.0167617751,
    "VarianceExplained": 0.0027248022
  },
  "dropped_9": {
    "CumulativeVarianceExplained": 0.5843858388,
    "Mask": "CSF",
    "Method": "aCompCor",
    "Retained": false,
    "SingularValue": 27.7562648126,
    "VarianceExplained": 0.0072494188
  },
  "dropped_90": {
    "CumulativeVarianceExplained": 0.9630531837,
    "Mask": "CSF",
    "Method": "aCompCor",
    "Retained": false,
    "SingularValue": 16.8653459882,
    "VarianceExplained": 0.0026765272
  },
  "dropped_91": {
    "CumulativeVarianceExplained": 0.965632146,
    "Mask": "CSF",
    "Method": "aCompCor",
    "Retained": false,
    "SingularValue": 16.5551044041,
    "VarianceExplained": 0.0025789623
  },
  "dropped_92": {
    "CumulativeVarianceExplained": 0.9681702458,
    "Mask": "CSF",
    "Method": "aCompCor",
    "Retained": false,
    "SingularValue": 16.4234267992,
    "VarianceExplained": 0.0025380999
  },
  "dropped_93": {
    "CumulativeVarianceExplained": 0.9706675598,
    "Mask": "CSF",
    "Method": "aCompCor",
    "Retained": false,
    "SingularValue": 16.2909345816,
    "VarianceExplained": 0.002497314
  },
  "dropped_94": {
    "CumulativeVarianceExplained": 0.9731163726,
    "Mask": "CSF",
    "Method": "aCompCor",
    "Retained": false,
    "SingularValue": 16.1319632337,
    "VarianceExplained": 0.0024488128
  },
  "dropped_95": {
    "CumulativeVarianceExplained": 0.9755487922,
    "Mask": "CSF",
    "Method": "aCompCor",
    "Retained": false,
    "SingularValue": 16.0778757269,
    "VarianceExplained": 0.0024324195
  },
  "dropped_96": {
    "CumulativeVarianceExplained": 0.9778797016,
    "Mask": "CSF",
    "Method": "aCompCor",
    "Retained": false,
    "SingularValue": 15.7388186927,
    "VarianceExplained": 0.0023309095
  },
  "dropped_97": {
    "CumulativeVarianceExplained": 0.9801758718,
    "Mask": "CSF",
    "Method": "aCompCor",
    "Retained": false,
    "SingularValue": 15.6210946833,
    "VarianceExplained": 0.0022961702
  },
  "dropped_98": {
    "CumulativeVarianceExplained": 0.9823829441,
    "Mask": "CSF",
    "Method": "aCompCor",
    "Retained": false,
    "SingularValue": 15.3150247505,
    "VarianceExplained": 0.0022070723
  },
  "dropped_99": {
    "CumulativeVarianceExplained": 0.9845793611,
    "Mask": "CSF",
    "Method": "aCompCor",
    "Retained": false,
    "SingularValue": 15.2780111714,
    "VarianceExplained": 0.002196417
  },
  "global_signal": {
    "Method": "Mean"
  },
  "t_comp_cor_00": {
    "CumulativeVarianceExplained": 0.3632079639,
    "Method": "tCompCor",
    "Retained": true,
    "SingularValue": 474.3999125976,
    "VarianceExplained": 0.3632079639
  },
  "t_comp_cor_01": {
    "CumulativeVarianceExplained": 0.5292820468,
    "Method": "tCompCor",
    "Retained": true,
    "SingularValue": 320.7878055067,
    "VarianceExplained": 0.1660740829
  },
  "tcompcor": {
    "Method": "Mean"
  },
  "white_matter": {
    "Method": "Mean"
  }
}